Workbook

Sheet Anti
F1: Common [C] | I1: Common [C] | L1: Uncommon [UC]
B3: 1 | C3: C O M M O N | D3: CHA | F3: 140 | G3: Alternative Normality | I3: 120 | J3: Weird Whisperer | L3: 100 | M3: Excentricity | P3: 140 | Q3: Scarecrow | U3: 130 | V3: Harmless Fatale | Z3: 120 | AA3: Threatening Presence | AE3: 110 | AF3: Freakshow
D4: Non | F4: =F3 -> 140 | I4: =I3 -> 120 | L4: 100 | O4: Appearence | P4: CAR | Q4: Damn!, you are scary, your whole deamenor gives you that dangerous look and ungodly aura, and it can be a really useful sometimes | U4: CAR | V4: Despite your clear lack of charisma, you project a clear aura and image of begin has deadly as a hamster, this triggers protective instincts from people of the "oposite sex" which can be good or bad depending on the circumstance (bad beucase you look unreliable and good beucase you can inspire protective instincts), however anyone that falls into this image/prejudice actively will grant the user a circumstance bonus. its applied to both social and non-social bases circumstances, even a sneak attack will add a bonus. CANNOT be taken with Scarecrow Anti-Perk | Z4: CAR | AA4: You look as someone who is dangerous, perhaps a thug, perhaps a criminal or a madman ready to stab someone, in simple terms no one wants to be near you by simple fear of you freaking out in public, even animals will react accordingly and guards will often stop you to ask about your business | AE4: CAR | AF4: You cause natural aphaty and rejection from people, its not nesesarily your looks but also you deamenor and voice, all of it composes a very misleading image to the point where you would rather speak behind a curtain. You have a natural "Aggro" aura that confuses and drives anyone to be hostile toward you, this is not applicable to "declared allies" or allies who can identify the user, but most neutral units will be confused and disconserted
F5: =F4-25 -> 115 | I5: =I4-20 -> 100
D6: CHA | E6: Aparence | F6: 135 | G6: Scarecrow | I6: 115 | J6: Aggro Caller | L6: 100 | M6: Haunted Crow | P6: Common[C] Anti-Perk | Q6: * - CAR 120: cu | U6: Common[C] Anti-Perk | V6: * - CAR 110: cu | Z6: UnCommon[UC] Anti-Perk | AA6: * - CAR 100: c | AE6: Rare[R] Anti-Perk | AF6: * - BASE: en
D7: Non | F7: =F6 -> 135 | I7: 115 | L7: 100 | Q7: * - Counter: en | V7: * - Counter: en | AA7: * - Counter: Las | AF7: REQ: Intimidating Presence + Stereotyping
F8: =F7-25 -> 110 | I8: 100
B9: 2 | D9: CHA | E9: Thrill | F9: 130 | G9: Devil-s Luck | I9: 115 | J9: Dangerous Atraction | L9: 100 | M9: Dare-Devil | P9: 140 | Q9: Innocently Insensitive | U9: 130 | V9: Unbeliveable | Z9: 120 | AA9: Natural Menace | AE9: 110 | AF9: Sociophaty for Fun | AK9: AGI
D10: Non | F10: =F9 -> 130 | I10: 115 | L10: 100 | O10: Emphaty | P10: CAR | Q10: a Flawled capacity for emphaty in the ability to detect, decipher and comprehend emotion may be a blessing in disguise, you have a natural resistance toward charisma based attacks such as war cry, intimidation and charm | U10: CAR | V10: You try your hardest to tell someone the truth but you simply and plainly are rather shady looking and with face saying that "im a scammer", you are simply unbelibeable but this can work on your advantage as people will regard you as a uncertain factor | Z10: CAR | AA10: you project THAT image, you look shady as hell, as if you are scheming something, you are clearly the villian in people's eye. You gain natural reputation toward the vilified and rejections of society, your charisma works as if it was much higher | AE10: CAR | AF10: ?????? | AK10: - Lame
F11: =F10-25 -> 105 | I11: 100 | AK11: - Lucky Clumsy
D12: CHA | E12: Feeling | F12: 140 | G12: Nerd Rage | I12: 120 | J12: Euphoria | L12: 100 | M12: Jekil & Hyde | P12: Common[C] Anti-Perk | Q12: * - CAR 120: cu | U12: Common[C] Anti-Perk | V12: * - CAR 110: cu | Z12: UnCommon[UC] Anti-Perk | AA12: * - CAR 100: c | AE12: Rare[R] Anti-Perk | AF12: * - BASE: en | AK12: - Trembling nads
D13: Non | F13: =F12 -> 140 | I13: =I12 -> 120 | L13: 100 | Q13: * - Counter: en | V13: * - Counter: en | AA13: * - Counter: Las | AF13: REQ: Natural Menace + Dangerous Attraction | AK13: - Klurtz
F14: =F13-25 -> 115 | I14: =I13-20 -> 100 | AK14: - Slow Mo
B15: 3 | D15: CHA | E15: Comm | F15: 140 | G15: DeadPan | I15: 120 | J15: Insensitive | L15: 100 | M15: Unimportant | P15: 140 | Q15: Motormouth | U15: 130 | V15: Noise Cancel | Z15: 120 | AA15: The Bore | AE15: 110 | AF15: Gargoyle Mumbling
D16: Non | F16: =F15 -> 140 | I16: =I15 -> 120 | L16: 100 | O16: Communication | P16: CAR | Q16: you speak unnaturally fast, you mouth also moves before you think!, its easy to screw things up but in exchange you reduce the time used for the "Verbal" component of most actions, any pure verbal action will be reduced in execution by 60%, while any action with a partial verbal component is reduced by 30% in average. | U16: CAR | V16: Your words have a particular tone and accent which people find annoying, its like a screech in the background or a white noise that plays as you talk. However, your mouth has the power to cancel other charisma attacks or intercept sound based debacles. You got a group falling asleep for a hypnotic lullaby, then just talk normally and the effect will dminish or be cancelled altogether | Z16: CAR | AA16: This is a person whose conversation is so dull, you would rather watch paint dry for an hour than listen to them for a minute. This works like a charm as a Charisma based attack toward the "Willpower" attribute, temporarily reducing the enemy attribute and even softening any mental resilence by lowering the awareness | AE16: CAR | AF16: ??????
F17: =F16-25 -> 115 | I17: =I16-20 -> 100 | AJ17: cdc
D18: WIL | E18: Focus | F18: 140 | G18: Useful Compulsion | I18: 120 | J18: Positive Obsesion | L18: 100 | M18: Adictive Enlightment | P18: Common[C] Anti-Perk | Q18: * - CAR 120: cu | U18: Common[C] Anti-Perk | V18: * - CAR 110: cu | Z18: UnCommon[UC] Anti-Perk | AA18: * - CAR 100: c | AE18: Rare[R] Anti-Perk | AF18: * - BASE: en
D19: Non | F19: =F18 -> 140 | I19: =I18 -> 120 | L19: 100 | Q19: * - Counter: en | V19: * - Counter: en | AA19: * - Counter: Las | AF19: REQ: The Bore + Scarecrow
P21: 140 | Q21: Whisperer Chain | U21: 130 | V21: Silence is Gold | Z21: 120 | AA21: Stone Mask | AE21: 110 | AF21: Silent Accomplice
O22: Silence | P22: CAR | Q22: your words lose power the more you talk, anything more than 5 words makes your words become weak and dilluited as if your voice was drowned into a whisper. | U22: CAR | V22: When you are silent and not moving, you produce a special charisma based aura effect, this aura effect varies according to the other people mood, in other words, some people will see the person as scary and some will feel him begin imposing, while others will feel presured, its all in the imagination of the onlooker, however, the mood in the room will affect this effect in great measure. A character with high willpower score 350+ are inmune to this effect. This effect is mantained as long as the user is silent and his actions work in line with the target perception | Z22: CAR | AA22: Your face is disconected from your emotional side just enough so it becomes your personal trademark. your heart burns but your face never shows, this leads to a heightened dificulty on "Sense motive" against you and other skill that read the character mood a severe penalty to skills used to express your emotions | AE22: CAR | AF22: ?????
P24: Common[C] Anti-Perk | Q24: * - CAR 120: cu | U24: Common[C] Anti-Perk | V24: * - CAR 110: cu | Z24: UnCommon[UC] Anti-Perk | AA24: * - CAR 100: c | AE24: Rare[R] Anti-Perk | AF24: * - BASE: en
Q25: * - Counter: en | V25: * - Counter: en | AA25: * - Counter: Las | AF25: REQ: Stone Mask +Clown Ears
P27: 140 | Q27: Stereotyping | U27: 130 | V27: Clown Ears | Z27: 120 | AA27: Karmic Hideout | AE27: 110 | AF27: Almost Faceless
O28: Prejudice | P28: CAR | Q28: Whenever you can fall into a stereotype your mark believes in (such as that orcs are brutal and cruel, women are scared and helpless, or that halflings are all thieves, etc.), you end up fitting and flowing with it thus againing advantage in social instances. This bonus is not cumulative if several prejudices can be used at once. For example, if your mark believes that halflings are scared and helpless, and that women are also scared and helpless you will only gain one single prejudice type even if you have both qualities (woman and halfling in the example). but this breaks once you take a clear action that defies this notion. | U28: CAR | V28: you apear to be a natural clown in your responses and deamenor, and due to your low charisma this makes others perceive you as a joke. However in exchange people will become talkactive and easily confide in you, sometimes beyond their own will | Z28: CAR | AA28: you have such low charisma and your actions are so clearly directed with prejudice that they hide a single truth: your alignment becomes obscured, and it cannot be exactly judged from your actions. With the exception of clear cut actions such as murder most people will classify you as morally grey and have different views on your alignment and general disposition, this not only obscures the alignment itself but also some traits such as a killer bloodlust or a paladin goodness | AE28: CAR | AF28: ??????
P30: Common[C] Anti-Perk | Q30: * - CAR 120: cu | U30: Common[C] Anti-Perk | V30: * - CAR 110: cu | Z30: UnCommon[UC] Anti-Perk | AA30: * - CAR 100: c | AE30: Rare[R] Anti-Perk | AF30: * - BASE: en
Q31: * - Counter: en | V31: * - Counter: en | AA31: * - Counter: Las | AF31: REQ: Karmic Hideout + Bland
P33: 140 | Q33: Dangerous Atraction | U33: 130 | V33: Bland | Z33: 120 | AA33: Innate Troll | AE33: 110 | AF33: Storm Caller
P34: CAR | Q34: You tend to attract the attention of the wrong crowd, and even when doing nothing will become socially interwited with people of questionable nature and dangerous inclination | U34: CAR | V34: You have no features, no distinctive presence you are almost forgeteable, and this can become a blessing to you. Bland makes the user hard to identify and easily pass unnoticed when walking in a crowd. You gain a passive stealth bonus when moving in a group of people, moreover, you add a hard penalty to identify or mark you | Z34: CAR | AA34: you easily speak the wrong things and have the uncanny nature to call into social problems, you will make exactly the wrong comment at the wrong time, and sometimes unknownly you will simply step on the proverbial dragons tail just by doing something completly mundane, its a curse and sometimes a boon | AE34: CAR | AF34: ????
O35: Magnetism
P36: Common[C] Anti-Perk | Q36: * - CAR 120: cu | U36: Common[C] Anti-Perk | V36: * - CAR 110: cu | Z36: UnCommon[UC] Anti-Perk | AA36: * - CAR 100: c | AE36: Rare[R] Anti-Perk | AF36: * - BASE: en
Q37: * - Counter: en | V37: * - Counter: en | AA37: * - Counter: Las | AF37: REQ: Innate Troll + Innocently Insensitive
F38: =F19-25 -> 115 | I38: =I19-20 -> 100
B39: 4 | D39: WIL | E39: Cowardice | F39: 135 | G39: Practical Cowardice | L39: 100 | M39: Fear Trigger | P39: 140 | Q39: Clever Idiot | U39: 130 | V39: Lucky Idiot | Z39: 120
D40: Non | F40: =F39 -> 135 | L40: 100 | P40: INT | U40: INT | V40: The Fool's strength is almost a supernatural fortune bordering on Karma. Since The Fool is such a person, nothing bad happens to him | Z40: INT
F41: =F40-25 -> 110 | O41: Idiot | AE41: 100
D42: WIL | F42: 135 | L42: 100 | M42: Curse Magnet | P42: Common[C] Anti-Perk | Q42: * - INT 115: cu | U42: Common[C] Anti-Perk | V42: * - CAR 100: cu | Z42: UnCommon[UC] Anti-Perk | AA42: * - CAR 100: c | AE42: INT
D43: Non | L43: 100 | Q43: * - Counter: en | V43: * - Counter: en | AA43: * - Counter: Las
AE44: Rare[R] Anti-Perk | AF44: * - BASE: en
B45: 5 | D45: WIL | L45: 100 | P45: 140 | Q45: Primal Impulse | U45: 130 | Z45: 120 | AF45: * - Counter: en
D46: Non | L46: 100 | O46: Instinct | P46: INT | Q46: La razon bloquea el camino hacia la naturaleza instintiva, interna y primitiva, el impulso primal conecta con los antiguos instinto dormidos para bien o para mal | U46: INT | Z46: INT
D48: WIL | L48: 100 | P48: Common[C] Anti-Perk | Q48: * - CAR 110: cu | U48: Common[C] Anti-Perk | V48: * - CAR 110: cu | Z48: UnCommon[UC] Anti-Perk | AA48: * - CAR 100: c | AE48: 100
D49: Non | L49: 100 | Q49: * - Counter: en | V49: * - Counter: en | AA49: * - Counter: Las | AE49: INT
B51: 6 | D51: INT | E51: Idea | F51: 135 | G51: Ignorance is Power | I51: 115 | J51: Thought Police | L51: 100 | M51: Double-Thinking | P51: 140 | Q51: Innocent Judgement | U51: 130 | Z51: 120 | AE51: Rare[R] Anti-Perk | AF51: * - BASE: en
D52: Non | F52: =F51 -> 135 | I52: 115 | L52: 100 | P52: INT | Q52: You see the evil in their eyes, the cockiness in that smirk, and the deceit in their voices that some of the other characters just can't see | U52: INT | Z52: INT | AF52: * - Counter: en
F53: =F52-25 -> 110 | I53: 100 | O53: Judgement
D54: INT | E54: Instinct | F54: 140 | G54: Primary Impulse | I54: 125 | J54: Reason Free | L54: 100 | P54: Align: GOOD | Q54: * - BASE: Gain a +5 aganist evil aligned characters in matters regarding social judgement, such as bluffing, diplomacy, negotiation, or simply by etc. Your character simply doubts and guards aganist these people by mistrusting them altogether. The user does not know who is evil actually or anything from the get go, but the skill activates when interacting in such a way where the target triest to convince the user in some way | U54: Common[C] Anti-Perk | V54: * - CAR 120: cu | Z54: UnCommon[UC] Anti-Perk | AA54: * - CAR 100: c
D55: Non | F55: =F54 -> 140 | I55: =I54 -> 125 | L55: 100 | P55: Common[C] Anti-Perk | Q55: * - INT 110: bonus aganist to a total of +10 aganist evil, and +2 aganist neutral | V55: * - Counter: en | AA55: * - Counter: Las
F56: =F55-25 -> 115 | I56: =I55-20 -> 105 | Q56: * - Counter: Tiendes a ser credulo con personajes de alineamiento bueno, tu resistencia a diplomacia, bluff, regateo o simplemente el pasar juicio imparcial sobre algun tema te quita -5 pts. Esto implica que para alguien de INT 140, su capacidad pasiva de "judgement" o juicio imparcial es tan solo "3" o menos
B57: 7 | D57: INT | E57: smart | F57: 130 | G57: Lucky Idiot | I57: 115 | J57: Clever Idiot | L57: 100 | M57: Enlighted Idiot | P57: 140 | U57: 130 | Z57: 120
D58: Non | F58: =F57 -> 130 | I58: 115 | L58: 100 | P58: PER | U58: PER | Z58: PER
F59: =F58-25 -> 105 | I59: 100 | AE59: 103
D60: INT | E60: Judgement | F60: 135 | G60: Innocent Judgement | I60: 120 | J60: Naive Logic | L60: 100 | P60: Common[C] Anti-Perk | Q60: * - CAR 100: cu | U60: Common[C] Anti-Perk | V60: * - CAR 100: cu | Z60: UnCommon[UC] Anti-Perk | AA60: * - CAR 100: c | AE60: PER
D61: Non | F61: =F60 -> 135 | I61: =I60 -> 120 | L61: 100 | Q61: * - Counter: en | V61: * - Counter: en | AA61: * - Counter: Las
F62: =F61-25 -> 110 | I62: =I61-20 -> 100 | AE62: Rare[R] Anti-Perk | AF62: * - BASE: en
B63: 8 | D63: INT | E63: coherence | F63: 140 | G63: Wrong Logic | I63: 125 | J63: Self-Deception | L63: 100 | M63: Blind Zealotry | P63: 140 | U63: 130 | Z63: 120 | AF63: * - Counter: en
D64: Non | F64: =F63 -> 140 | I64: =I63 -> 125 | L64: 100 | P64: PER | U64: PER | Z64: PER
F65: =F64-25 -> 115 | I65: =I64-20 -> 105
P66: Common[C] Anti-Perk | Q66: * - CAR 100: cu | U66: Common[C] Anti-Perk | V66: * - CAR 110: cu | Z66: UnCommon[UC] Anti-Perk | AA66: * - CAR 100: c | AE66: 103
Q67: * - Counter: en | V67: * - Counter: en | AA67: * - Counter: Las | AE67: PER
L68: RARE | M68: Orwellian Nature
B69: 9 | L69: ??? | P69: 140 | U69: 130 | Z69: 120 | AE69: Rare[R] Anti-Perk | AF69: * - BASE: en
P70: PER | U70: PER | Z70: PER | AF70: * - Counter: en
P72: Common[C] Anti-Perk | Q72: * - CAR 100: cu | U72: Common[C] Anti-Perk | V72: * - CAR 120: cu | Z72: UnCommon[UC] Anti-Perk | AA72: * - CAR 100: c
Q73: * - Counter: en | V73: * - Counter: en | AA73: * - Counter: Las
L74: RARE | M74: Philosopher Fool
B75: 10 | L75: ??? | P75: 140 | U75: 130 | Z75: 120
P76: STR | U76: STR | Z76: STR
AE77: 110
P78: Common[C] Anti-Perk | Q78: * - CAR 100: cu | U78: Common[C] Anti-Perk | V78: * - CAR 100: cu | Z78: UnCommon[UC] Anti-Perk | AA78: * - CAR 100: c | AE78: STR
Q79: * - Counter: en | V79: * - Counter: en | AA79: * - Counter: Las
L80: RARE | M80: Misplaced Faith | AE80: Rare[R] Anti-Perk | AF80: * - BASE: en
B81: 11 | L81: ??? | P81: 140 | U81: 130 | Z81: 120 | AF81: * - Counter: en
P82: STR | U82: STR | Z82: STR
P84: Common[C] Anti-Perk | Q84: * - CAR 100: cu | U84: Common[C] Anti-Perk | V84: * - CAR 110: cu | Z84: UnCommon[UC] Anti-Perk | AA84: * - CAR 100: c | AE84: 110
Q85: * - Counter: en | V85: * - Counter: en | AA85: * - Counter: Las | AE85: STR
B87: 12 | P87: 140 | U87: 130 | Z87: 120 | AE87: Rare[R] Anti-Perk | AF87: * - BASE: en
P88: STR | U88: STR | Z88: STR | AF88: * - Counter: en
P90: Common[C] Anti-Perk | Q90: * - CAR 100: cu | U90: Common[C] Anti-Perk | V90: * - CAR 120: cu | Z90: UnCommon[UC] Anti-Perk | AA90: * - CAR 100: c
Q91: * - Counter: en | V91: * - Counter: en | AA91: * - Counter: Las
P93: 140 | Q93: Cynical Ruling | U93: 130 | Z93: 120 | AA93: Tinfoil Hatter | AE93: 110
P94: WIL | Q94: the world is big and very magical, but you just cannot see that side, your character will normalize supernatural phenomena and be exceptical about most magical phenomena. This is very good when dealing with supernatural fears and nightmares as the user will simply reject them altogether in most cases | U94: WIL | Z94: WIL | AA94: You are that guy, the one who is or was ambrushed by aliens/magical races/traveled in time and thus become aware of a very dangerous aspect of the world. You can actually use your pseudo-paranoia to find the strangest things since you are actually looking for them | AE94: WIL
O95: Weird
O96: Supernat | P96: Common[C] Anti-Perk | Q96: * - WIL 120: cu | U96: Common[C] Anti-Perk | V96: * - CAR 105: cu | Z96: UnCommon[UC] Anti-Perk | AA96: * - CAR 100: c | AE96: Rare[R] Anti-Perk | AF96: * - BASE: en
Q97: * - Counter: en | V97: * - Counter: en | AA97: * - Counter: Las | AF97: * - Counter: en
P99: 140 | Q99: Hyper Optimist | U99: 130 | Z99: 120 | AA99: Spiteful Crisis | AE99: 110 | AJ99: Weird World | AL99: Happy Camper | AN99: Power Spot | AP99: supernat
P100: WIL | Q100: Some people say that you have no pride as you are very capable of ignoring slangs and insults. This is beucase you are convinced that your are weak by nature (regardless of the truth in this). You will simply accept the insult in a very positive manner as a way to improve yourself, to challenge yourself and become stronger | U100: WIL | Z100: WIL | AA100: You are narrowminded and spiteful and thus when bad things happen you have "negative energy tank" that accumulates the bad things, this is then transformed into spite and grudges which the user can direct to others. In simple terms by accumulating mental damage the user will use the power of the grudge to their advantage | AE100: WIL | AJ100: * - you have the touch. You always find the most strange stuff out there, as if you attracted the stuff on purpuse. Which stuff ? It can be from ruins to relics, to monsters, to people. The only common element> they are all damn WEIRD!. This feat does not grant any percivable bonus, just WEIRD ??? | AL100: * - the stress and penalty for living and travelling on a wilderness is reduced | AN100: * - Leyline Discovery -
O101: Stoic | AJ101: Stoic | AL101: Iron Will | AN101: Pain Tolerance | AP101: Wil
O102: Iron Will | P102: Common[C] Anti-Perk | Q102: * - WIL 120: cu | U102: Common[C] Anti-Perk | V102: * - CAR 125: cu | Z102: UnCommon[UC] Anti-Perk | AA102: * - CAR 100: c | AE102: Rare[R] Anti-Perk | AF102: * - BASE: en | AJ102: you gain a bonus based on your alignement, this bonus counters actions that go against your alignment. Thus a evil character may resist "Redeption" if the player wishes so | AL102: * - you have an iron will, bonus on any defensive roll where you will is tested | AN102: * - when resisting pain, injury and wound you can reduce the penalty.
Q103: * - Counter: en | V103: * - Counter: en | AA103: * - Counter: Las | AF103: * - Counter: en | AJ103: Strong Soul | AL103: Impartial Belief | AN103: Mana Rejection | AP103: Inner
AJ104: * - Strong Soul - | AL104: * - you try your best to be impartial and not judgemental | AN104: * - you reject mana by sheer will, reducing magic based damage
P105: 140 | Q105: Cloud Head | U105: 130 | Z105: 120 | AE105: 110
O106: muddled | P106: WIL | Q106: A character with their head in the clouds. They are strangely oblivious to things that everyone else takes for granted. | U106: WIL | Z106: WIL | AE106: WIL
O107: /Focus
P108: Common[C] Anti-Perk | Q108: * - WIL 120: cu | U108: Common[C] Anti-Perk | V108: * - CAR 105: cu | Z108: UnCommon[UC] Anti-Perk | AA108: * - CAR 100: c | AE108: Rare[R] Anti-Perk | AF108: * - BASE: en
Q109: * - Counter: en | V109: * - Counter: | AA109: * - Counter: Las | AF109: * - Counter: en
P111: 140 | U111: 130 | Z111: 120 | AE111: 110
O112: Impartial | P112: WIL | U112: WIL | Z112: WIL | AE112: WIL
P114: Common[C] Anti-Perk | Q114: * - WIL 120: cu | U114: Common[C] Anti-Perk | V114: * - CAR 105: cu | Z114: UnCommon[UC] Anti-Perk | AA114: * - CAR 100: c | AE114: Rare[R] Anti-Perk | AF114: * - BASE: en
Q115: * - Counter: en | V115: * - Counter: en | AA115: * - Counter: Las | AF115: * - Counter: en
P117: 140 | U117: 130 | Z117: 120 | AE117: 110
...

Sheet Groups
AR4: 0 | AS4: =IFERROR(INDEX($C$5:$C$64,AR4*12+1),INDEX($M$5:$M$64,(AR4-4)*12+1)) -> WARRIOR | AT4: =CONCATENATE(LEFT(AS4,1),MID(LOWER(AS4),2,LEN(AS4))) -> Warrior
A5: 1 | C5: WARRIOR | D5: Melee Weapons Handling | H5: STR | I5: AGI | J5: STR- BODY - SPRT | M5: BRAWLER | N5: Brawling | R5: AGI | T5: AGI - BODY - SPRT | AR5: 1 | AS5: =IFERROR(INDEX($C$5:$C$64,AR5*12+1),INDEX($M$5:$M$64,(AR5-4)*12+1)) -> ROUGE | AT5: =CONCATENATE(LEFT(AS5,1),MID(LOWER(AS5),2,LEN(AS5))) -> Rouge
A6: 2 | Y6: =D9 -> Athletism | AB6: =H9 -> AGI | AC6: =COUNTIF($D$5:$Q$64,Y6)+COUNTIF($D$69:$V$149,Y6) -> 2 | AD6: =C5 -> WARRIOR | AF6: =M5 -> BRAWLER | AH6: =IF(IFNA(VLOOKUP(Y6,$Y7:Y$70,1,FALSE),"-")=Y6,"Duplicate","-") -> - | AK6: Athletism | AN6: AGI | AR6: 2 | AS6: =IFERROR(INDEX($C$5:$C$64,AR6*12+1),INDEX($M$5:$M$64,(AR6-4)*12+1)) -> MAGE | AT6: =CONCATENATE(LEFT(AS6,1),MID(LOWER(AS6),2,LEN(AS6))) -> Mage
A7: 3 | D7: Heavy Armor Handling | H7: STR | N7: Still Mind, Focus | R7: WIL | Y7: =S108 -> Intimidation | AB7: =W108 -> WIL | AC7: =COUNTIF($D$5:$Q$64,Y7)+COUNTIF($D$69:$V$149,Y7) -> 2 | AD7: =C5 -> WARRIOR | AH7: =IF(IFNA(VLOOKUP(Y7,$Y8:Y$70,1,FALSE),"-")=Y7,"Duplicate","-") -> - | AK7: Hide | AN7: AGI | AR7: 3 | AS7: =IFERROR(INDEX($C$5:$C$64,AR7*12+1),INDEX($M$5:$M$64,(AR7-4)*12+1)) -> SORCEROR | AT7: =CONCATENATE(LEFT(AS7,1),MID(LOWER(AS7),2,LEN(AS7))) -> Sorceror
A8: 4 | Y8: =D13 -> Discipline | AB8: =H13 -> WIL | AC8: =COUNTIF($D$5:$Q$64,Y8)+COUNTIF($D$69:$V$149,Y8) -> 2 | AD8: =C5 -> WARRIOR | AF8: =C53 -> PRIEST | AH8: =IF(IFNA(VLOOKUP(Y8,$Y9:Y$70,1,FALSE),"-")=Y8,"Duplicate","-") -> - | AK8: Sleight of Hand | AN8: AGI | AR8: 4 | AS8: =IFERROR(INDEX($C$5:$C$64,AR8*12+1),INDEX($M$5:$M$64,(AR8-4)*12+1)) -> PRIEST | AT8: =CONCATENATE(LEFT(AS8,1),MID(LOWER(AS8),2,LEN(AS8))) -> Priest
A9: 5 | D9: Athletism | H9: AGI | N9: Discipline | R9: WIL | Y9: =D21 -> Alert | AB9: =H21 -> PER | AC9: =COUNTIF($D$5:$Q$64,Y9)+COUNTIF($D$69:$V$149,Y9) -> 2 | AD9: =C17 -> ROUGE | AH9: =IF(IFNA(VLOOKUP(Y9,$Y10:Y$70,1,FALSE),"-")=Y9,"Duplicate","-") -> - | AK9: Dismantle | AN9: AGI | AR9: 5 | AS9: =IFERROR(INDEX($C$5:$C$64,AR9*12+1),INDEX($M$5:$M$64,(AR9-4)*12+1)) -> EXPLORER | AT9: =CONCATENATE(LEFT(AS9,1),MID(LOWER(AS9),2,LEN(AS9))) -> Explorer
A10: 6 | Y10: =D25 -> Hide | AB10: =H25 -> AGI | AC10: =COUNTIF($D$5:$Q$64,Y10)+COUNTIF($D$69:$V$149,Y10) -> 2 | AD10: =C17 -> ROUGE | AF10: =M17 -> EXPLORER | AH10: =IF(IFNA(VLOOKUP(Y10,$Y11:Y$70,1,FALSE),"-")=Y10,"Duplicate","-") -> - | AK10: Riding | AN10: AGI | AR10: 6 | AS10: =IFERROR(INDEX($C$5:$C$64,AR10*12+1),INDEX($M$5:$M$64,(AR10-4)*12+1)) -> BARD | AT10: =CONCATENATE(LEFT(AS10,1),MID(LOWER(AS10),2,LEN(AS10))) -> Bard
A11: 7 | D11: Battle | H11: PER | N11: Rest | R11: STR | Y11: =D33 -> Spellcraft | AB11: =H33 -> PER | AC11: =COUNTIF($D$5:$Q$64,Y11)+COUNTIF($D$69:$V$149,Y11) -> 2 | AD11: =C29 -> MAGE | AF11: =K87 -> Mystic | AH11: =IF(IFNA(VLOOKUP(Y11,$Y12:Y$70,1,FALSE),"-")=Y11,"Duplicate","-") -> - | AK11: Intimidation | AN11: CAR | AR11: 7 | AS11: =IFERROR(INDEX($C$5:$C$64,AR11*12+1),INDEX($M$5:$M$64,(AR11-4)*12+1)) | AT11: =CONCATENATE(LEFT(AS11,1),MID(LOWER(AS11),2,LEN(AS11)))
A12: 8 | Y12: =D37 -> Mental Focus | AB12: =H37 -> WIL | AC12: =COUNTIF($D$5:$Q$64,Y12)+COUNTIF($D$69:$V$149,Y12) -> 3 | AD12: =C29 -> MAGE | AF12: =C81 -> Showman | AH12: =IF(IFNA(VLOOKUP(Y12,$Y13:Y$70,1,FALSE),"-")=Y12,"Duplicate","-") -> - | AK12: Spirit Sensitivity | AN12: CAR
A13: 9 | D13: Discipline | H13: WIL | I13: STR | N13: Athletism | R13: AGI | Y13: =D35 -> Magic Obj | AB13: =H35 -> INT | AC13: =COUNTIF($D$5:$Q$64,Y13)+COUNTIF($D$69:$V$149,Y13) -> 2 | AD13: =C29 -> MAGE | AH13: =IF(IFNA(VLOOKUP(Y13,$Y14:Y$70,1,FALSE),"-")=Y13,"Duplicate","-") -> - | AK13: Bluff | AN13: CAR
A14: 10 | Y14: =D57 -> Spirit Sensitivity | AB14: =H57 -> CAR | AC14: =COUNTIF($D$5:$Q$64,Y14)+COUNTIF($D$69:$V$149,Y14) -> 2 | AD14: =C53 -> PRIEST | AH14: =IF(IFNA(VLOOKUP(Y14,$Y15:Y$70,1,FALSE),"-")=Y14,"Duplicate","-") -> - | AK14: Perform | AN14: CAR
A15: 11 | Y15: =D59 -> Healing | AB15: =H59 -> WIL | AC15: =COUNTIF($D$5:$Q$64,Y15)+COUNTIF($D$69:$V$149,Y15) -> 3 | AD15: =C53 -> PRIEST | AH15: =IF(IFNA(VLOOKUP(Y15,$Y16:Y$70,1,FALSE),"-")=Y15,"Duplicate","-") -> - | AK15: Animal Empathy | AN15: CAR
A16: 12 | Y16: =D23 -> Bluff | AB16: =H23 -> CAR | AC16: =COUNTIF($D$5:$Q$64,Y16)+COUNTIF($D$69:$V$149,Y16) -> 2 | AD16: =M5 -> BRAWLER | AF16: =K81 -> Minstrel | AH16: =IF(IFNA(VLOOKUP(Y16,$Y17:Y$70,1,FALSE),"-")=Y16,"Duplicate","-") -> - | AK16: Diplomacy | AN16: CAR
A17: 13 | C17: ROUGE | D17: Light Weapons Handling | H17: AGI | J17: AGI -BODY - MIND | M17: EXPLORER | N17: Projectile Weapons Handling | R17: PER | T17: PER - BODY - MIND | Y17: =N11 -> Rest | AB17: =R11 -> STR | AC17: =COUNTIF($D$5:$Q$64,Y17)+COUNTIF($D$69:$V$149,Y17) -> 2 | AD17: =M5 -> BRAWLER | AF17: =M53 -> DRUID | AH17: =IF(IFNA(VLOOKUP(Y17,$Y18:Y$70,1,FALSE),"-")=Y17,"Duplicate","-") -> Duplicate | AK17: Haggle | AN17: CAR
Y18: =N23 -> Trapper | AB18: =R23 -> INT | AC18: =COUNTIF($D$5:$Q$64,Y18)+COUNTIF($D$69:$V$149,Y18) -> 2 | AD18: =M17 -> EXPLORER | AH18: =IF(IFNA(VLOOKUP(Y18,$Y19:Y$70,1,FALSE),"-")=Y18,"Duplicate","-") -> - | AK18: Acting | AN18: CAR
D19: Light Armor Handling | H19: STR | I19: AGI | N19: Light Armor Handling | R19: STR | AD19: =M17 -> EXPLORER | AH19: =IF(IFNA(VLOOKUP(Y19,$Y20:Y$70,1,FALSE),"-")=Y19,"Duplicate","-") -> - | AK19: Temptation | AN19: CAR
Y20: =N33 -> Sleight of Hand | AB20: =R33 -> AGI | AC20: =COUNTIF($D$5:$Q$64,Y20)+COUNTIF($D$69:$V$149,Y20) -> 2 | AD20: =M29 -> BARD | AF20: =R69 -> Thief | AH20: =IF(IFNA(VLOOKUP(Y20,$Y21:Y$70,1,FALSE),"-")=Y20,"Duplicate","-") -> - | AK20: Magic Obj | AN20: INT
D21: Alert | H21: PER | N21: Dismantle | R21: AGI | Y21: =N35 -> Perform | AB21: =R35 -> CAR | AC21: =COUNTIF($D$5:$Q$64,Y21)+COUNTIF($D$69:$V$149,Y21) -> 2 | AD21: =M29 -> BARD | AF21: =K81 -> Minstrel | AH21: =IF(IFNA(VLOOKUP(Y21,$Y22:Y$70,1,FALSE),"-")=Y21,"Duplicate","-") -> - | AK21: Trapper | AN21: INT
Y22: =L71 -> Culture Lore | AB22: INT | AC22: =COUNTIF($D$5:$Q$64,Y22)+COUNTIF($D$69:$V$149,Y22) -> 2 | AD22: =M29 -> BARD | AF22: =K81 -> Minstrel | AH22: =IF(IFNA(VLOOKUP(Y22,$Y23:Y$70,1,FALSE),"-")=Y22,"Duplicate","-") -> - | AK22: Culture Lore | AN22: INT
D23: Bluff | H23: CAR | N23: Trapper | R23: INT | Y23: =S112 -> Wilderness | AB23: WIL | AC23: =COUNTIF($D$5:$Q$64,Y23)+COUNTIF($D$69:$V$149,Y23) -> 3 | AD23: =M53 -> DRUID | AF23: =R112 -> Survivalist | AH23: =IF(IFNA(VLOOKUP(Y23,$Y24:Y$70,1,FALSE),"-")=Y23,"Duplicate","-") -> - | AK23: Astrology | AN23: INT
Y24: =L91 -> Astrology | AB24: =P91 -> INT | AC24: =COUNTIF($D$5:$Q$64,Y24)+COUNTIF($D$69:$V$149,Y24) -> 3 | AD24: =M53 -> DRUID | AF24: =K87 -> Mystic | AH24: =IF(IFNA(VLOOKUP(Y24,$Y25:Y$70,1,FALSE),"-")=Y24,"Duplicate","-") -> - | AK24: Court | AN24: INT
D25: Hide | H25: AGI | N25: Alert | R25: PER | Y25: Battle | AB25: PER | AC25: =COUNTIF($D$5:$Q$64,Y25)+COUNTIF($D$69:$V$149,Y25) -> 2 | AH25: =IF(IFNA(VLOOKUP(Y25,$Y26:Y$70,1,FALSE),"-")=Y25,"Duplicate","-") -> - | AK25: Craft | AN25: INT
Y26: Cooking | AB26: =H69 -> WIL | AC26: =COUNTIF($D$5:$Q$64,Y26)+COUNTIF($D$69:$V$149,Y26) -> 2 | AH26: =IF(IFNA(VLOOKUP(Y26,$Y27:Y$70,1,FALSE),"-")=Y26,"Duplicate","-") -> - | AK26: Formal Magics | AN26: INT
Y27: Animal Empathy | AB27: =IFNA(VLOOKUP(Y27,$L$69:$P$92,5,FALSE),VLOOKUP(Y27,$D$69:$H$80,5,FALSE)) -> CAR | AC27: =COUNTIF($D$5:$Q$64,Y27)+COUNTIF($D$69:$V$149,Y27) -> 4 | AH27: =IF(IFNA(VLOOKUP(Y27,$Y28:Y$70,1,FALSE),"-")=Y27,"Duplicate","-") -> - | AK27: Herbalism | AN27: INT
Y28: Apraisal | AB28: =H91 -> PER | AC28: =COUNTIF($D$5:$Q$64,Y28)+COUNTIF($D$69:$V$149,Y28) -> 2 | AH28: =IF(IFNA(VLOOKUP(Y28,$Y29:Y$70,1,FALSE),"-")=Y28,"Duplicate","-") -> - | AK28: Knowledge (Specific) | AN28: INT
C29: MAGE | D29: Basic Mana Discipline | H29: INT | J29: MIND2 | M29: BARD | N29: Mana Sensitivity | R29: WIL | T29: CAR - SPR - BODY | Y29: Climbing | AB29: =W73 -> STR | AC29: =COUNTIF($D$5:$Q$64,Y29)+COUNTIF($D$69:$V$149,Y29) -> 2 | AH29: =IF(IFNA(VLOOKUP(Y29,$Y30:Y$70,1,FALSE),"-")=Y29,"Duplicate","-") -> - | AK29: Linguistics | AN29: INT
AH30: =IF(IFNA(VLOOKUP(Y30,$Y31:Y$70,1,FALSE),"-")=Y30,"Duplicate","-") -> - | AK30: Mechanics | AN30: INT
D31: Mana Sensitivity | H31: PER | I31: WIL | N31: Melee Weapons Handling | R31: STR | Y31: Craft | AB31: =P93 -> INT | AC31: =COUNTIF($D$5:$Q$64,Y31)+COUNTIF($D$69:$V$149,Y31) -> 1 | AH31: =IF(IFNA(VLOOKUP(Y31,$Y32:Y$70,1,FALSE),"-")=Y31,"Duplicate","-") -> - | AK31: Lockpick | AN31: INT
Y32: Diplomacy | AB32: =IFNA(VLOOKUP(Y32,$L$69:$P$92,5,FALSE),VLOOKUP(Y32,$D$69:$H$80,5,FALSE)) -> #N/A | AC32: =COUNTIF($D$5:$Q$64,Y32)+COUNTIF($D$69:$V$149,Y32) -> 2 | AH32: =IF(IFNA(VLOOKUP(Y32,$Y33:Y$70,1,FALSE),"-")=Y32,"Duplicate","-") -> - | AK32: Alert | AN32: PER
D33: Spellcraft | H33: PER | N33: Sleight of Hand | R33: AGI | Y33: Dismantle | AB33: =IFNA(VLOOKUP(Y33,$L$69:$P$92,5,FALSE),VLOOKUP(Y33,$D$69:$H$80,5,FALSE)) -> #N/A | AC33: =COUNTIF($D$5:$Q$64,Y33)+COUNTIF($D$69:$V$149,Y33) -> 2 | AH33: =IF(IFNA(VLOOKUP(Y33,$Y34:Y$70,1,FALSE),"-")=Y33,"Duplicate","-") -> - | AK33: Spellcraft | AN33: PER
Y34: Farming | AB34: =IFNA(VLOOKUP(Y34,$L$69:$P$92,5,FALSE),VLOOKUP(Y34,$D$69:$H$80,5,FALSE)) -> WIL | AC34: =COUNTIF($D$5:$Q$64,Y34)+COUNTIF($D$69:$V$149,Y34) -> 1 | AH34: =IF(IFNA(VLOOKUP(Y34,$Y35:Y$70,1,FALSE),"-")=Y34,"Duplicate","-") -> - | AK34: Battle | AN34: PER
D35: Magic Obj | H35: INT | N35: Perform | R35: CAR | Y35: Formal Magics | AB35: =P87 -> INT | AC35: =COUNTIF($D$5:$Q$64,Y35)+COUNTIF($D$69:$V$149,Y35) -> 1 | AH35: =IF(IFNA(VLOOKUP(Y35,$Y36:Y$70,1,FALSE),"-")=Y35,"Duplicate","-") -> - | AK35: Apraisal | AN35: PER
Y36: Haggle | AB36: =H89 -> CAR | AC36: =COUNTIF($D$5:$Q$64,Y36)+COUNTIF($D$69:$V$149,Y36) -> 2 | AH36: =IF(IFNA(VLOOKUP(Y36,$Y37:Y$70,1,FALSE),"-")=Y36,"Duplicate","-") -> - | AK36: Investigation | AN36: PER
D37: Mental Focus | H37: WIL | N37: Diplomacy | R37: CAR | Y37: HandiCraft | AB37: =W114 -> STR | AC37: =COUNTIF($D$5:$Q$64,Y37)+COUNTIF($D$69:$V$149,Y37) -> 2 | AH37: =IF(IFNA(VLOOKUP(Y37,$Y38:Y$70,1,FALSE),"-")=Y37,"Duplicate","-") -> - | AK37: Sense Motive | AN37: PER
Y38: Herbalism | AB38: =H97 -> INT | AC38: =COUNTIF($D$5:$Q$64,Y38)+COUNTIF($D$69:$V$149,Y38) -> 2 | AH38: =IF(IFNA(VLOOKUP(Y38,$Y39:Y$70,1,FALSE),"-")=Y38,"Duplicate","-") -> - | AK38: Streetwise | AN38: PER
Y39: Inclemence | AB39: =W85 -> STR | AC39: =COUNTIF($D$5:$Q$64,Y39)+COUNTIF($D$69:$V$149,Y39) -> 2 | AH39: =IF(IFNA(VLOOKUP(Y39,$Y40:Y$70,1,FALSE),"-")=Y39,"Duplicate","-") -> - | AK39: Tracking | AN39: PER
Y40: Investigation | AB40: =IFNA(VLOOKUP(Y40,$L$69:$P$92,5,FALSE),VLOOKUP(Y40,$D$69:$H$80,5,FALSE)) -> PER | AC40: =COUNTIF($D$5:$Q$64,Y40)+COUNTIF($D$69:$V$149,Y40) -> 3 | AH40: =IF(IFNA(VLOOKUP(Y40,Y53:$Y$70,1,FALSE),"-")=Y40,"Duplicate","-") -> - | AK40: Rest | AN40: STR
C41: SORCEROR | D41: Basic Mana Discipline | H41: CAR
D45: Astrology | H45: INT
D47: Animal Empathy | H47: CAR
D49: Mental Focus | H49: WIL
C53: PRIEST | D53: Holy Light, Faith | H53: CAR | J53: SPR2 | M53: DRUID | N53: Nature, Focus | R53: CAR | T53: CAR - SPR-BODY | Y53: Knowledge (Specific) | AB53: =IFNA(VLOOKUP(Y53,$L$69:$P$92,5,FALSE),VLOOKUP(Y53,$D$69:$H$80,5,FALSE)) -> INT | AC53: =COUNTIF($D$5:$Q$64,Y53)+COUNTIF($D$69:$V$149,Y53) -> 2 | AH53: =IF(IFNA(VLOOKUP(Y53,$Y54:Y$70,1,FALSE),"-")=Y53,"Duplicate","-") -> - | AK53: Climbing | AN53: STR
T54: Light Weapons Handling | Y54: Linguistics | AB54: =IFNA(VLOOKUP(Y54,$L$69:$P$92,5,FALSE),VLOOKUP(Y54,$D$69:$H$80,5,FALSE)) -> INT | AC54: =COUNTIF($D$5:$Q$64,Y54)+COUNTIF($D$69:$V$149,Y54) -> 1 | AH54: =IF(IFNA(VLOOKUP(Y54,$Y55:Y$70,1,FALSE),"-")=Y54,"Duplicate","-") -> - | AK54: HandiCraft | AN54: STR
D55: Piety | H55: WIL | N55: Light Weapons Handling | R55: AGI | Y55: Mechanics | AB55: =P105 -> INT | AC55: =COUNTIF($D$5:$Q$64,Y55)+COUNTIF($D$69:$V$149,Y55) -> 1 | AH55: =IF(IFNA(VLOOKUP(Y55,$Y56:Y$70,1,FALSE),"-")=Y55,"Duplicate","-") -> - | AK55: Inclemence | AN55: STR
T56: Healing | Y56: Minning | AB56: =P95 -> STR | AC56: =COUNTIF($D$5:$Q$64,Y56)+COUNTIF($D$69:$V$149,Y56) -> 2 | AH56: =IF(IFNA(VLOOKUP(Y56,$Y57:Y$70,1,FALSE),"-")=Y56,"Duplicate","-") -> - | AK56: Minning | AN56: STR
D57: Spirit Sensitivity | H57: CAR | N57: Healing | R57: WIL | Y57: Acting | AB57: =H81 -> CAR | AC57: =COUNTIF($D$5:$Q$64,Y57)+COUNTIF($D$69:$V$149,Y57) -> 1 | AH57: =IF(IFNA(VLOOKUP(Y57,$Y58:Y$70,1,FALSE),"-")=Y57,"Duplicate","-") -> - | AK57: REST | AN57: STR
T58: Rest | Y58: Riding | AB58: =W83 -> AGI | AC58: =COUNTIF($D$5:$Q$64,Y58)+COUNTIF($D$69:$V$149,Y58) -> 2 | AH58: =IF(IFNA(VLOOKUP(Y58,$Y59:Y$70,1,FALSE),"-")=Y58,"Duplicate","-") -> - | AK58: Discipline | AN58: WIL
D59: Healing | H59: WIL | N59: Rest | R59: STR | Y59: Sense Motive | AB59: =H85 -> PER | AC59: =COUNTIF($D$5:$Q$64,Y59)+COUNTIF($D$69:$V$149,Y59) -> 2 | AH59: =IF(IFNA(VLOOKUP(Y59,$Y60:Y$70,1,FALSE),"-")=Y59,"Duplicate","-") -> - | AK59: Mental Focus | AN59: WIL
T60: Animal Empathy | Y60: Streetwise | AB60: =H112 -> PER | AC60: =COUNTIF($D$5:$Q$64,Y60)+COUNTIF($D$69:$V$149,Y60) -> 2 | AH60: =IF(IFNA(VLOOKUP(Y60,$Y61:Y$70,1,FALSE),"-")=Y60,"Duplicate","-") -> - | AK60: Healing | AN60: WIL
D61: Knowledge (Specific) | H61: INT | N61: Animal Empathy | R61: CAR | AH61: =IF(IFNA(VLOOKUP(Y61,$Y62:Y$70,1,FALSE),"-")=Y61,"Duplicate","-") -> - | AK61: Wilderness | AN61: WIL
Y62: Tracking | AB62: =P101 -> PER | AC62: =COUNTIF($D$5:$Q$64,Y62)+COUNTIF($D$69:$V$149,Y62) -> 1 | AH62: =IF(IFNA(VLOOKUP(Y62,$Y63:Y$70,1,FALSE),"-")=Y62,"Duplicate","-") -> - | AK62: Cooking | AN62: WIL
Y63: Wayfarer | AB63: =W81 -> WIL | AC63: =COUNTIF($D$5:$Q$64,Y63)+COUNTIF($D$69:$V$149,Y63) -> 2 | AH63: =IF(IFNA(VLOOKUP(Y63,$Y64:Y$70,1,FALSE),"-")=Y63,"Duplicate","-") -> - | AK63: Farming | AN63: WIL
Y64: Lockpick | AB64: INT | AC64: =COUNTIF($D$5:$Q$64,Y64)+COUNTIF($D$69:$V$149,Y64) -> 1 | AH64: =IF(IFNA(VLOOKUP(Y64,$Y65:Y$70,1,FALSE),"-")=Y64,"Duplicate","-") -> - | AK64: Wayfarer | AN64: WIL
Y65: REST | AB65: =R59 -> STR | AC65: =COUNTIF($D$5:$Q$64,Y65)+COUNTIF($D$69:$V$149,Y65) -> 2 | AH65: =IF(IFNA(VLOOKUP(Y65,$Y66:Y$70,1,FALSE),"-")=Y65,"Duplicate","-") -> -
C69: Witch | D69: Cooking | H69: WIL | I69: SPR | K69: Lawmaker | L69: Investigation | P69: PER | Q69: MND | R69: Thief | S69: Lockpick | W69: INT | X69: BODY
D71: Spirit Sensitivity | H71: CAR | L71: Culture Lore | P71: INT | S71: Hide | W71: AGI
D73: Astrology | H73: INT | L73: Intimidation | P73: WIL | S73: Climbing | W73: STR
C75: Farmer | D75: Farming | H75: WIL | I75: SPR | K75: Academic | L75: Knowledge (Specific) | P75: INT | Q75: MIND | R75: Butcher | S75: Dismantle | W75: AGI | X75: BODY
D77: Animal Empathy | H77: CAR | L77: Investigation | P77: PER | S77: Cooking | W77: WIL
D79: Minning | H79: STR | L79: Linguistics | P79: INT | S79: HandiCraft | W79: STR
C81: Showman | D81: Acting | H81: CAR | I81: SPR | K81: Minstrel | L81: Perform | P81: CAR | Q81: MIND | R81: Traveller | S81: Wayfarer | W81: WIL | X81: BODY
D83: Mental Focus | H83: WIL | L83: Culture Lore | P83: INT | S83: Riding | W83: AGI
D85: Sense Motive | H85: PER | L85: Streetwise | P85: PER | S85: Inclemence | W85: STR
C87: Merchant | D87: Wayfarer | H87: WIL | I87: SPR | K87: Mystic | L87: Formal Magics | P87: INT | Q87: MIND | X87: BODY
D89: Haggle | H89: CAR | L89: Spellcraft | P89: PER
D91: Apraisal | H91: PER | L91: Astrology | P91: INT
C93: Pharmascist | D93: Haggle | H93: CAR | I93: SPR | K93: Artisan | L93: Craft | P93: INT | Q93: MIND
D95: Healing | H95: WIL | L95: Minning | P95: STR
D97: Herbalism | H97: INT | L97: Apraisal | P97: PER
C99: Savage | D99: Wilderness | H99: WIL | I99: SPR | K99: Hunter | L99: Wilderness | P99: WIL | Q99: MIND | X99: BODY
D101: Animal Empathy | H101: CAR | L101: Tracking | P101: PER
D103: Climbing | H103: STR | L103: Trapper | P103: INT
K105: Engineer | L105: Mechanics | P105: INT | Q105: MIND
R106: Merc | S106: Battle | W106: PER
L107: Magic Obj | P107: INT
S108: Intimidation | W108: WIL
L109: Investigation | P109: PER
S110: Inclemence | W110: STR
C112: Low Class | D112: Streetwise | H112: PER | K112: High Class | L112: Sense Motive | P112: PER | R112: Survivalist | S112: Wilderness | W112: WIL
D114: Bluff | H114: CAR | L114: Riding | P114: AGI | S114: HandiCraft | W114: STR
D116: Sleight of Hand | H116: AGI | L116: Diplomacy | P116: CAR | S116: Herbalism | W116: INT
X117: BODY

Sheet List
C3: Core Skills
B5: 1 | C5: Brawling | E5: =IFNA(VLOOKUP(C5,Groups!$D$5:$H$62,5,FALSE),VLOOKUP(C5,Groups!$N$5:$R$62,5,FALSE)) -> AGI
B6: 2 | C6: Light Weapons Handling | E6: =IFNA(VLOOKUP(C6,Groups!$D$5:$H$62,5,FALSE),VLOOKUP(C6,Groups!$N$5:$R$62,5,FALSE)) -> AGI | H6: Basic lv struct
B7: 3 | C7: Holy Light, Faith | E7: =IFNA(VLOOKUP(C7,Groups!$D$5:$H$62,5,FALSE),VLOOKUP(C7,Groups!$N$5:$R$62,5,FALSE)) -> CAR
B8: 4 | C8: Nature, Focus | E8: =IFNA(VLOOKUP(C8,Groups!$D$5:$H$62,5,FALSE),VLOOKUP(C8,Groups!$N$5:$R$62,5,FALSE)) -> CAR | H8: 1. Action open - raise 1
B9: 5 | C9: Basic Mana Discipline | E9: =IFNA(VLOOKUP(C9,Groups!$D$5:$H$62,5,FALSE),VLOOKUP(C9,Groups!$N$5:$R$62,5,FALSE)) -> INT | H9: 2. Skill check+1 -
B10: 6 | C10: Mana Sensitivity | E10: =IFNA(VLOOKUP(C10,Groups!$D$5:$H$62,5,FALSE),VLOOKUP(C10,Groups!$N$5:$R$62,5,FALSE)) -> PER | H10: 3. Skill performance+1 - item allowance
B11: 7 | C11: Projectile Weapons Handling | E11: =IFNA(VLOOKUP(C11,Groups!$D$5:$H$62,5,FALSE),VLOOKUP(C11,Groups!$N$5:$R$62,5,FALSE)) -> PER | H11: 4. Skill check+2 -
B12: 8 | C12: Heavy Armor Handling | E12: =IFNA(VLOOKUP(C12,Groups!$D$5:$H$62,5,FALSE),VLOOKUP(C12,Groups!$N$5:$R$62,5,FALSE)) -> STR | H12: 5. Skill Prof - Greater Check+1
B13: 9 | C13: Light Armor Handling | E13: =IFNA(VLOOKUP(C13,Groups!$D$5:$H$62,5,FALSE),VLOOKUP(C13,Groups!$N$5:$R$62,5,FALSE)) -> STR | I13: Skill becomes upgradeable 1
B14: 10 | C14: Melee Weapons Handling | E14: =IFNA(VLOOKUP(C14,Groups!$D$5:$H$62,5,FALSE),VLOOKUP(C14,Groups!$N$5:$R$62,5,FALSE)) -> STR | H14: 6. 1st Feat Requiered
B15: 11 | C15: Piety | E15: =IFNA(VLOOKUP(C15,Groups!$D$5:$H$62,5,FALSE),VLOOKUP(C15,Groups!$N$5:$R$62,5,FALSE)) -> WIL | I15: Action Enhance - greater perform
B16: 12 | C16: Still Mind, Focus | E16: =IFNA(VLOOKUP(C16,Groups!$D$5:$H$62,5,FALSE),VLOOKUP(C16,Groups!$N$5:$R$62,5,FALSE)) -> WIL | H16: 7. Skill performance+2 - raise 2
I17: Skill becomes upgradeable 2
H18: 8. Skill check+3 - attributes skill restric
C19: Aditional Skills | H19: 9. Skill performance+4 -
I20: Skill becomes upgradeable 3
B21: 1 | C21: Athletism | E21: =VLOOKUP(C21,Groups!$AK$6:$AN$64,4,FALSE) -> AGI | H21: 10. 2nd Feat Requiered
B22: 2 | C22: Dismantle | E22: =VLOOKUP(C22,Groups!$AK$6:$AN$64,4,FALSE) -> AGI | I22: Skill prof+, Mastery perk, Greater Check+2
B23: 3 | C23: Hide | E23: =VLOOKUP(C23,Groups!$AK$6:$AN$64,4,FALSE) -> AGI
B24: 4 | C24: Riding | E24: =VLOOKUP(C24,Groups!$AK$6:$AN$64,4,FALSE) -> AGI
B25: 5 | C25: Sleight of Hand | E25: =VLOOKUP(C25,Groups!$AK$6:$AN$64,4,FALSE) -> AGI
B26: 6 | C26: Acting | E26: =VLOOKUP(C26,Groups!$AK$6:$AN$64,4,FALSE) -> CAR
B27: 7 | C27: Animal Empathy | E27: =VLOOKUP(C27,Groups!$AK$6:$AN$64,4,FALSE) -> CAR
B28: 8 | C28: Bluff | E28: =VLOOKUP(C28,Groups!$AK$6:$AN$64,4,FALSE) -> CAR
B29: 9 | C29: Diplomacy | E29: =VLOOKUP(C29,Groups!$AK$6:$AN$64,4,FALSE) -> CAR
B30: 10 | C30: Haggle | E30: =VLOOKUP(C30,Groups!$AK$6:$AN$64,4,FALSE) -> CAR
B31: 11 | C31: Intimidation | E31: =VLOOKUP(C31,Groups!$AK$6:$AN$64,4,FALSE) -> CAR
B32: 12 | C32: Perform | E32: =VLOOKUP(C32,Groups!$AK$6:$AN$64,4,FALSE) -> CAR
B33: 13 | C33: Spirit Sensitivity | E33: =VLOOKUP(C33,Groups!$AK$6:$AN$64,4,FALSE) -> CAR
B34: 14 | C34: Astrology | E34: =VLOOKUP(C34,Groups!$AK$6:$AN$64,4,FALSE) -> INT
... B63: 43 | C63: Wayfarer | E63: =VLOOKUP(C63,Groups!$AK$6:$AN$64,4,FALSE) -> WIL

Sheet Sheet1

Sheet Skill Detail
C3: DISCIPLINE | E3: =VLOOKUP(C3,List!$C$5:$E$63,3,FALSE) -> WIL | L3: HIDE | N3: =VLOOKUP(L3,List!$C$5:$E$63,3,FALSE) -> AGI | U3: ATHLETISM | W3: =VLOOKUP(U3,List!$C$5:$E$63,3,FALSE) -> AGI | AD3: Melee Weapons | AF3: STR
C4: Action: | L4: Action: | U4: Action: | AD4: Action:
C5: Lv 1 | D5: Combat focus - resist fear and cohesion based spirit attacks automatically when in battle | M5: Hide in Cover - hide using "Heavy obstacles" such as walls, solid structures, etc. You need to cover your whole body to make it work | V5: Action Man: perform enhanced physical action such as Running, Jumping, etc. After the action there is a temporal fatigue debuff of 1 dice penalty, stackable | AE5: Melee Combat I:
C6: LV 6 | D6: C. Focus II - when in combat defend against distractions automatically | M6: Hide in Cover II - Hide using "Light obstacles" such as thin structures and furniture, you need to cover your whole body to make it work | V6: A.Man II - you can perform a extended Athetism action, until you stop there is no sudden fatigue penalty. Stopping means to have one round where you do not perform athetism actions or you fail your athetism skill check | AE6: Melee Combat II: | AL6: Action Man: perform enhanced physical action such as Running, Jumping, etc. After the action there is a temporal fatigue debuff of 1 dice penalty, stackable
C7: Lv 10 | D7: C. Focus III - react to fear outside of battle with a saving roll bonus | M7: Hide in Cover III - as long as you cover your body with a heavy or light obstacle at 75% it is considered covered and may be hidden | V7: A.Man III - allows to resist and reject the temporal fatigue defuff with a body saving roll, however next fatigue roll becomes harder to resist | AE7: Melee Combat III: | AL7: A.Man II - you can perform a extended Athetism action, until you stop there is no sudden fatigue penalty. Stopping means to have one round where you do not perform athetism actions or you fail your athetism skill check
C8: Evolution: | L8: Evolution: | U8: Evolution: | AD8: Evolution:
D9: Bravery(T1) | M9: Camoflage(T1) | V9: Sprinter(T1) | AE9: Pikemen Technique (T1)
D10: Soldiering (T2) | M10: Cloak&Dagger(T2) | V10: Acrobacy(T2) | AE10: Heavy Blade Technique (T1)
D11: Martial Temperance (T3) | M11: Hide in Plain Sight (T3) | V11: Heightened Balance (T3) | AE11: Battle Club Technique (T1)
D12: Warmonger (Rare) | M12: Unremarkable (Rare) | V12: Marathon (Rare) | AE12: Light Blade Technique (T1)
C13: Perform(1-5) | L13: Perform(1-4) | U13: Perform(1-4) | AE13: Footman Technique (T2)
D14: Start - Resist by 5 | M14: Start - Hide Cover Dificulty by 10 | V14: Start - Improve 25% of physical action | AE14: Heavy Soldier Technique (T2)
D15: 1. Resist by 10 | M15: 1. Hide Cover Dificulty by 15 | V15: 1. Improve 50% of physical action | AE15: Light Calvalry Technique (T2)
D16: 2. Skill Crit: On a skill check of 40 or more, add +10 to Resist Score | M16: 2. Skill Crit: On a skill check of 40 or more, add +10 to Hide Score | V16: 2. Skill Crit: On a skill check of 40 or more, add +50% to physical action performance | AE16: Barbarian Vandal Technique (T3)
D17: 3. Resist by 15 | M17: 3. Hide Cover Dificulty by 20 | V17: 3. Improve 75% of physical action | AE17: Guardian Soldier Technique (T3)
D18: G.Perf - Reaction: you gain a +5 morale bonus on attack rolls and weapon damage rolls the fear affect on you for 1 round. Non Stackable | M18: G.Perf - ?? | V18: G.Perf - Reduces the amount of Fatigue produced by a Highly physical action | AE18: Twin Blade Technique (Rare)
E19: Reaction: Whenever a fear effect targets you and fails to affect you | M19: 4. Hide Cover Dificulty by 25 | V19: 4. Improve 100% of physical action | AE19: Oriental Spear Technique (Rare)
D20: 4. Resist by 20 | M20: 5. Skill Crit: On a skill check of 50 or more, add +10 to Hide Score | V20: 2. Skill Crit: On a skill check of 50 or more, add +100% to physical action performance | AD20: Perform(1-4)
D21: 5. Skill Crit 2: On a skill check of 50 or more, add +15 to Resist Score, Reaction doubles bonus and it last for 3 rounds | AE21: Start -
C22: Proficiency (1-7) | L22: Proficiency (1-7) | U22: Proficiency (1-7)
D23: 1. Discipline item: well mantained and functional battle gear grants +1 per piece to skill check up to a max of +3 | M23: 1. Hide Item: Hide skills can be used | V23: 1. Athletism Item: Specific footwear item can boost athletism
D24: 2. Group Bravery: When fighting in groups the morale of others may strenghten your will based skills | M24: 2. Step in shadows - shadows grant bonus | V24: 2.
D25: 3. Soldier's Resilence: The character's focus and discipline allow them to reduce fatigue penalty temporarily for 1 scene using discipline skill checks | M25: 3. Hide in shadows - deep shadows are used as a light cover obstacle | V25: 3.
D26: 4. Against The Wall: When the character is bellow 25% of his HP, his abilities explode into an ability boost during a number of rounds equal to your will/50 | M26: 4. Peek a boo - you peek around objects without loosing cover | V26: 2.
D27: 5. Stoic reticence: your discipline skill will trigger automatically even against ambrushes and other effects that you are not aware of., however, you still need to be on guard and alert to danger for this to happen so a complete ambrush will still leave you defenseless | M27: 5. Shadow switch - you can change covers as a free action when no one is looking within 3 mts. Only once per round | V27: 3.
D28: 6. Combat Discipline: The character's discipline in combat allows them to slightly reduce non-supernatural physical damage they are aware of based on the WILL score | M28: 6. Quick shadow - you can exit stealth cover to perform a single action such as steal or attack within 3 mts then return to your stealth on the same round | V28: 2.
D29: 7. Iron Heart: your mind and heart have been trained throughtly, in any mind-affecting effect over you which has a skill check with less than 40, you will reduce one rank in the effect or otherwise halve the duration of the effect. this only works in mind or enchantment skills which are rejected using will or spirit based rolls | M29: 7. One with shadows - when in shadows special perk become active | V29: 3.
C32: Healing | E32: =VLOOKUP(C32,List!$C$5:$E$63,3,FALSE) -> WIL | L32: Battle | N32: =VLOOKUP(L32,List!$C$5:$E$63,3,FALSE) -> PER | U32: Magic Obj | W32: INT | AD32: Mana Sensitivity | AF32: WIL
C33: Action: | L33: Action: | U33: Action: | AD33: Action:
D34: Patching : During a "Short Rest" (aprox 2hrs) period, you can recover additional (1k1) to target, it works only once per target after any "Long Rest" (8hrs), multiple healings cannot be stacked together. You can only heal as many as your WILL/50 people during a single short rest, while still resting yourself. otherwise, you can manage twice as much people but with no rest and adding a permanent fatigue penalty debuff | M34: Battle Tactics : in combat battle tactics can be used to spot combat oportunities and asset when the enemy is working to obtain an advantage. For example: in the next round, if you do not move from this area you will be blocked off from escape, and one round later you will be surrounded. A simple tactical superiority will offer additional circumstantial bonus to the user during a specific frame of time, on the other hand a obtaining a clear "advantage" such surrounding, or a high ground with a ranged weapon will either have the user roll twice and choose the best roll or directly take away dice from the target | V34: Magic Exec I: you can activate and use most "useable" and "non bonded" magic items. It takes 10-20 rounds to sync with the magic item for the first time and from then on, 1-3 round of syncing before using the magic object after that. You need to spend 1mp at least to activate a magic item, a character incapable of providing at least this much cannot activate the item. Please keep in mind that different magic items have a different "magic obj" level to be used and some requiere far more MP to be activated. | AE34: Mana Trigger: As a Full-Round Action, you can use this ability to actively sense other Mana-users out to a range of 1 meters x compound skill level. If you succeed on a DC 15 Mana sensitivity check, you know how many Mana-users are within range, their approximate distance and direction from you. Another Mana-user within range can try to conceal his or her presence from you by making an opposed Mana Sensitivity check. The higher and more vulgar the display of mana the easier is to sense and localize this presence, you can imagine it as a sixth sence which triggers automatically in reaction to mana. This is very useful to find mana rich locations, items and even to react to sudden mana attacks such as mana based traps. This action is limited to "ACTIVE" mana skills which are cast or target near the user, and will not register PASSIVE mana skills or abilities which are already at work continuosly beforehand
D35: Patching II : Reduces penalty when dealing with open wound injuries such as bleeding. Allows the healer to restore a small amount of "WOUND" type damage | M35: Battle Tactics II: your can add your battle roll score when performing combat teamwork tactics or, in case that the user is the combat leader: looking for team-type combat oportunities. However, please beware that this only works if the group is willingly working together and has some means to comunicate or has time to perform some adjustments. Team type combat oportunities can only be taken when the leader has a Battle skill on this same level at the very least | V35: Magic Exec II: you can now interact with structural magical objects such as elevators, magic aparatus and other magic objects which are not in the tool or human-class type (objects made to be worn by humans). You are still limited to interact with "useable" and "non bonded" magic structures. Please keep in mind that some magic aparatus such as transportation devices (teleport facility), requiere large amount of mana to work. it takes 10-20 rounds to sync with newly met magical objects, however, it will take usually 1-3 rounds after the first time (depending on the object complexity). | AE35: Mana Trigger II: As a Full-Round Action, you can enter a ManaTrance with a DC 10 mana sensitivity check. In this state, you remain fully aware of your surroundings. Each hour you remain in the trance, you regain a number of Mana Points equal to your Mana Sensitivity Level (max 10)
D36: Patching III : you can perform Patching outside of a "short rest" instance by spending 10 minutes in performing a total focus action, the user is completly prone during that time, and will remain prone during 3 rounds after suspending treatment. However, the target must abide by a non-intensive physical action policy, otherwise the effect will be voided and the target must be healed again with heavy penalty, HP recovered in this way is only "temporarily" recovered until the hour time has passed which is when the recovery becomes permanent | M36: Battle Tactics III: When you are in a disvantageous tactical circumstance you can reduce the imposed penalty by quickly adapting to it and adjusting your actions acordingly. If you perform the appropiate actions, then, reduce the penalty imposed by the combat disvantage | V36: Magic Exec III: you can de-activate and interrupt the use of most "non-useable" magical objects, these objects will normally trigger by themselves but you are capable of trigger them down, most of the time this means the expenditure of MP to interrupt the flow of mana of the object. it takes from 5-10 rounds to interrupt a magical object and you need to be in contact with it or its magical core. Also, please keep in mind that even non-useable magical objects are made to be worn by humans, this skill does not allow the user to interact with "autonomous" and "independent" magical objects such as golems and magic traps | AE36: Magic Trigger III: As a Full round action, you can enter into total defense mode where you obtain +5 to your mana saving roll, this is provided that you can actually move and react to it. This action reflects the user attunement to the mana so high that he can react instinctively to mana based attacks and dodge as if he knew the attack was comming beforehand.
D37: Note: Healing[C] cannot treat someone with "Serious wounds"(R4) or worse | M37: *note: Battle[c] can be used in both Large scale battle and normal combat, but its effects are different for both, the effects described here detail about its use in "normal combat" | V37: *note: Useable items are magical items which accept external inputs, for example, a ring of protection is a "non-useable" item as it provides a constant magical bonus, and there is no manipulation from the user toward the ring, in simple terms, the ring simply works by putting it on your finger and there is no enabling or disabling. Viceversa, a useable item such as a magic wand needs the user to activate and sometimes guide its powers | AE37: *note2: Mana sensitivity has a base cost of 3 MP per use for the unskilled person who has learned it recently
C38: Evolution: | L38: Evolution: | V38: *note2: please keep in mind that any magical object that has not been sync with the user in a time equal to a 1 day (4 TU) will count as a new magical object | AD38: Evolution:
D39: Combat Aid(T1) | M39: Combat Coordination (T1) | U39: Evolution: | AE39: Mana Body (T1)
D40: Treatment(T2) | M40: Skirmirsher (T2) | V40: Multi-Magic Object (T1) | AE40: Mana Trance (T1)
D41: Diagnose (T3) | M41: Leadership (T3) | V41: MagicShieldUser (T1) | AE41: Mana Sense (T2)
D42: Oriental Healing (Rare) | M42: Guerrilla Warfare (Rare) | V42: Scrying Eye (T1) | AE42: Mana Attunement (T2)
C43: Perform(1-4) | L43: Perform(1-4) | V43: WandWielder (T2) | AE43: Superior Mana Sensitivity (T3)
D44: Start - Recover 1k1 HP of health | M44: Start - Detect Combat Oportunities | V44: Magic Devise Operation (T2) | AD44: Perform(1-4)
D45: 1. Meding Effect I: mend bleeding wounds and stabilize health hazards or injuries ranked "minor"(R1) as base (more by performing raises) | M45: 1. Flatfooted I: an enemy caught in a combat oportunity becomes flat-footed (-5 to armor rating, minimun: 5 + Armor bonus) | V45: Devise Canceller (T3) | AE45: Start - 1 meter x compound skill level
D46: 2. Skill Crit: On a skill check of 40 or more, add targets +VIT/2 to healing and mend one rank higher of wounds (max: serious wounds) | M46: 2. Skill Crit: On a skill check of 40 or more, if the target is caught on a combat oportunity in favor to the player, the target is forced to roll a saving roll using MIND or yield a "combat Advantage" to the user during 1 round. Only once per combat. the target saving roll is half of the current critical roll value with a maximun of 40. A target which has the Battle skill will reduce this dificulty by half again and will use his Battle roll to resist | V46: Mana-based Relic (Rare) | AE46: 1. Sensitivity Up I: 2 meter x compound skill level
D47: 3. Meding Effect II: mend bleeding wounds and stabilize health hazards, only injuries ranked from "Minor"(R1) to "Light"(R2) as base (more by performing raises) | M47: 3. Flatfooted II: an enemy caught in a combat oportunity becomes flat-footed (-10 to armor rating, minimun: 5 + Armor bonus) | U47: Perform(1-4) | AE47: 2. Skill Crit 1: On a skill check of 40 or more, increases every mana sensitivity action by 50% (increases Range by 50%, MP gained by 50%, and defense score by 50%)
D48: G.Perf I - Recover additional health by target +Vit score | M48: G. Perf I - When commanding, leading or otherwise guiding a group where every member is willingly collaborating, then you add a bonus to the team Armor rating. The bonus is usually equal to each member perception score /100. Please keep in mind that any member that breaks away from the team is not covered in this benefit, moreover, breaking away from the group may break the team formation and cancel the bonus for every member altogether. a Maximun of user Perception/100+1 people can be benefited in this way | V48: Start - 10-20 round for new activation, 1 round of sync for known sync | AE48: 3. Sensitivity Up II: 3 meter x compound skill level
D49: 4. Meding Effect III: mend bleeding wounds and stabilize health hazards, only injuries ranked from "Minor"(R1) to "Moderate"(R3) as base (more by performing raises) | M49: 4. Flatfooted III: an enemy caught in a combat oportunity becomes flat-footed (-15 to armor rating, minimun: 5 + Armor bonus) | V49: 1. Activation Sync I: Reduce activation time by 50%, minimun 1 round of sync | AE49: G. Perf I - Reduce mana sensitivity cost to 1 MP
D50: 5. Skill Crit 2: On a skill check of 50 or more, add targets +VIT to healing and Gains a Free Raise when rolling effect | M50: 5. Skill Crit 2: On a skill check of 50 or more, if the target is caught on a combat oportunity in favor to the player, the target is forced to roll a saving roll using MIND or yield a "combat Advantage" to the user during until 3 rounds, the target may roll each round to become free of this by spending a round to compose himself or enter a total defense stance. Can be used many times in a single combat but only once against a single target. the target saving roll is half of the current critical roll value with a maximun of 40. A target which has the Battle skill will not receive any additional bonus, but can use his "Battle roll" to resist | V50: 2. Skill Crit 1: On a skill check of 40 or more, the activation time is shortened by 25% and the user will add a +5 to initiative | AE50: 4. Sensitivity Up III: 5 meter x compound skill level
C51: Proficiency (1-7) | L51: Proficiency (1-7) | V51: 3. Activation Sync II: Reduce activation time by 75%, minimun 0 round of sync | AE51: 5. Skill Crit 2: On a skill check of 50 or more, increases every mana sensitivity action by 100% (increases Range by 100%, MP gained by 100%, and defense score by 100%)
D52: 1. Healing Item: Bandages and cleaning products | M52: 1. Battle Item: Usable and context appropiate maps and telescope or other perception tools for the battlefield | V52: G. Perf I - Reduce the activation cost by 50%, a mana cost of 1 becomes 0mp, however, multiple activations will count as 0.5 each rounded up. This does not affect the item when using external energy source unless the user is capable of interacting and manipulating the source | AD52: Derivate Bonus
D53: 2. Medical Application: When using medicines and restoratives which need to be "applied" the user increases the effective perform rating of the medicine. This does not work on potions and other autonomous medicine | M53: 2. | V53: 3. Activation Sync III: Reduce activation time by 90%, minimun 0 round of sync | AD53: * Spells an abilities based on Mana Sensitivity
D54: 3. Germaphobe: When working on a clean and sterile environment your medical skills gain a free raise, a clean room as many other perks to medicine, this bonus is simply a synergy between medic and proper environment. | M54: 3. | V54: 5. Skill Crit 2: On a skill check of 50 or more, the activation time is shortened additional 50% and the user will add a +10 to initiative. (for example a 90%
D55: 4. Savior Complex: When performing a life threathening emergency procedure, you gain a instant +0k1 to your healing dice roll | M55: 4. | U55: Proficiency (1-7)
D56: 5. Clinically Trained: you have reached a industrial level handling and efficiency when dealing with patients, you take half the time in treating anyone. In some skills such as "basic healing" this means double the amount of people handled during a period of time (short break) | M56: 5. | V56: 1. Magic Object Item: Non magical Items endowed with mana and mana stones
D57: 6. Full Metal Medic: You can ignore 2 dice of penalty due wounds or fatigue when performing medical acts and only medical acts. | M57: 6. | V57: 2.
D58: 7. Superior Medical Care: you can perform 2 medical actions simultaneously toward a single target patient, this does increase the dificulty of performancy by 5 pts (similar to a Raise). It works as follows: if the "first medical actions succeeds, then the second medical action is automatically a success too, but if the first medical action fails then only the first medical actions penalties and fail conditions are met", please keep in mind that this method is automatic for a doctor and is considered the default action. Moreover, when two medical actions are choosen the one with the highest dificulty is set as the base dificulty. NOTE: a doctor with only one hand or movility problems will have large penalty when using this advantage | M58: 7. | V58: 3.
C59: FEATS (1-4) | L59: FEATS (1-4) | V59: 4.
D60: Medical Inmobilizing : your patching can now inmobilize and partially restore mobility to damaged limbs, these limbs have not recovered but become stable enough to walk/move and will not cause damage to the patient when performing normal actions, however, the target must abide by a non-intensive physical action policy while using these limbs, otherwise the effect will be voided and the target must be healed again with heavy penalty. This action/skill cannot heal dead limbs or limbs with a "serious wound"(R4) or worse | V60: 5.
V61: 6.
V62: 7.
C63: Mechanic | E63: INT | U63: FEATS (1-4)
C64: Action:
D65: Mechanical Keen I: Most mechanical items are tools from human-class type (objects made to be worn by humans), and thus they are of medium or small size and usually are of the "simple type" and thus they can be used without the need of this skill, for simple mechanical items this skill may be used to perform maintenance, however, complex mechanical items and Larger mechanical objects such as machines (for example a Mobile devise (like an automobile), need a mechanical keen in order to be used. this skill allows to use a wide variety of complex mechanical objects in a fixed "begginer level of skill". the complexity of the object establishes the level of skill needed to use. Please keep in mind that a begginer level of skill is at most something roughly barely enough to use any object with little presition so most objects requiere a superior and more specialized skill such as driving. | AD65: you have become able to "Discover" the hidden magic elements sleeping in the world, this means you can uncover mana which is at work concurrently and continuously such as ilutions, barriers and other continual magic. This allows the user FIND and discover hidden locations or treasures by reading continual magic pulse, this only works along with magically induced hidden locations or places where mana was used to hide something. Example: a mana based mechanism used to move a wall, a fake wall created by mana, a mana trap which is active a waiting to be shot, an antennae or altar which is the core of a barrier or another continual area mana power.
D66: Mechanical Keen II: During a "Short Rest" (aprox 2hrs) period, you can perform mechanical repair on a mechanical type object or structure, the mechanical repairs will restore some of the object durability, however, it cannot recover durability above a certain threshold without the use of spare parts and pieces, you can repair as many as INT/100 +1 simple objects in a single short break, or twice if you do not rest at all (this earns 1 ranks of temporal fatigue). Repairing any object under 50% of its durability without the use of spare parts or raw materials has a high chance to permanently reducing its max durability even in a succesful repair roll. Please keep in mind | AD66: you are capable of "feeling" the common elements simply known as "Mana", and this allows you to be aware of any character who uses mana in their surroundings as well as the use of any magical object. The higher and more vulgar the display of mana the easier is to sense and localize this presence, you can imagine it as a sixth sence which triggers automatically in reaction to mana. This is very useful to find mana rich locations, items and even to react to sudden mana attacks such as mana based traps. In general terms the master will inform the players about sudden mana spikes nearby the user and their general direction and the user will automatically react to this stimulus, in a very vulgar display of power such as high discharge mana cannons the user may be even able to tell the target location of the cannon shot. This action is limited to "ACTIVE" mana skills which are cast or target near the user, and will not register PASSIVE mana skills or abilities which are already at work continuosly beforehand
D67: Mechanical Keen III : you are capable of purpusely making a mechanical item "malfunction", it may be as simple as a wagon wheel collapsing in the right moment or a simple mechanical item misfiring in the worst moment, the targeted malfunction is useful to perform sabotage actions, but also to disable mechanical traps and other simple mechanical obstacles. Please keep in mind that the user needs access to the mechanical "core" of the object, otherwise its very dificult to allow a mechanical misfire, so a totally armored mechanical object which has its core perfectly locked is rampaging on the loose, this skill can only be useful if there is a way to access it. Moreover, like any mechanical skill it can only tamper with IRON ranked mechanical items, and bronze ranked are out of your league.
D68: Note: Mechanic[C] cannot repair or mend an object with a high complexity (Bronze rank or above) or any object with a damage equivalent to "Serious Malfunction"(R4) or worse
C69: Evolution:
D70: Drive(T1)
D71: Cannoner(T1)
D72: Mechanical Operation(T2)
D73: Mechanical Sabotagee(T2)
D74: Tinkerer (T3)
D75: Mana Mechanics (T3)
D76: Alien Mechanics (Rare)
C77: Perform(1-4)
D78: Start -
D79: 1.
D80: 5. Skill Crit 1:
D81: 3.
D82: G.Perf I -
D83: 4.
D84: 5. Skill Crit 2:
C85: Proficiency (1-7)
D86: 1. Mechanical Item: Engineering tool sets such as wrench, screedriver, grease, oil, etc and other tools sets used by engineers.
D87: 2.
D88: 3.
D89: 4.
D90: 5.
D91: 6.
D92: 7.
C93: FEATS (1-4)

Sheet Sheet3
C5: Basic lv struct
C7: 1. Action open - raise 1 | G7: 1 | H7: Raise 1 | J7: Patching : During a "Short Rest" (aprox 2hrs) period, you can recover additional (1k1) to target, it works only once per target after any "Long Rest" (8hrs), multiple healings cannot be stacked together. You can only heal as many as your WILL/50 people during a single short rest, while still resting yourself. otherwise, you can manage twice as much people but with no rest and adding a permanent fatigue penalty debuff | N7: 10's Explode | R7: Combat focus - resist fear and cohesion based spirit attacks automatically when in battle
C8: 2. Skill check+1 - | R8: C. Focus II - when in combat defend against distractions automatically
C9: 3. Skill performance+1 - item allowance | G9: 2 | H9: Skill Check +1 | J9: Meding Effect I: mend bleeding wounds and stabilize health hazards or injuries ranked "minor"(R1) as base (more by performing raises)
C10: 4. Skill check+2 - | R10: Skill Check 1k0+3
C11: 5. Skill Prof - Greater Check+1 | G11: 3 | H11: SKILL PROF 1: Healing Item | J11: Skill Crit 1: On a skill check of 40 or more, add targets +VIT/2 to healing and mend one rank higher of wounds (max: serious wounds)
C12: Skill becomes upgradeable 1 | R12: Raise 2
C13: 6. 1st Feat Requiered | G13: 4 | H13: Skill Check +2 | J13: Meding Effect II: mend bleeding wounds and stabilize health hazards, only injuries ranked from "Minor"(R1) to "Light"(R2) as base (more by performing raises)
C14: Action Enhance - greater perform | R14: 2. Skill Crit: On a skill check of 40 or more, add +10 to Resist Score
C15: 7. Skill performance+2 - raise 2 | G15: 5 | H15: Skill Check 1k0+2 | N15: SKILL UPGRADE I | R15: 3. Resist by 15
C16: Skill becomes upgradeable 2 | R16: G.Perf - Reaction: you gain a +5 morale bonus on attack rolls and weapon damage rolls the fear affect on you for 1 round. Non Stackable
C17: 8. Skill check+3 - attributes skill restric
C18: 9. Skill performance+4 - | H18: REQUIERES 1st FEAT
C19: Skill becomes upgradeable 3 | G19: 6 | H19: Skill Check 1k0+3 | J19: Patching II : you can perform Patching outside of a "short rest" instance by spending 10 minutes in performing a total focus action, the user is completly prone during that time, and will remain prone during 3 rounds after suspending treatment. However, the target must abide by a non-intensive physical action policy, otherwise the effect will be voided and the target must be healed again with heavy penalty, HP recovered in this way is only "temporarily" recovered until the hour time has passed which is when the recovery becomes permanent
C20: 10. 2nd Feat Requiered | R20: Acrobacia | T20: Lv 1 [8]
C21: Skill prof+, Mastery perk, Greater Check+2 | G21: 7 | H21: Raise 2 | J21: G. Enhace: Recover additional health by target +Vit score | N21: SKILL UPGRADE II | R21: 1k0+3 | S21: Skill Actions:
S22: ActionMan - perform enhanced physical action such as Running, Jumping, etc. After the action there is a temporal fatigue debuff of 1 dice penalty, stackable
S23: ActionMan II - you can perform a extended Athetism action, until you stop there is no sudden fatigue penalty. Stopping means to have one round where you do not perform athetism actions or you fail your athetism skill check
H24: REQUIERES 2nd FEAT | R24: Check | S24: JumpMan -
G25: 8 | H25: Skill Check 1k0+4 | J25: Meding Effect III: mend bleeding wounds and stabilize health hazards, only injuries ranked from "Minor"(R1) to "Moderate"(R3) as base (more by performing raises) | R25: 2 | S25: Skill Traits
S26: - Improve 75% of physical action
G27: 9 | H27: SKILL PROF 2: Healing Item | J27: Skill Crit 2: On a skill check of 50 or more, add targets +VIT to healing and Gains a Free Raise when rolling effect | N27: SKILL UPGRADE III | R27: Raises | S27: - Reduces the amount of Fatigue produced by a Highly physical action
R28: 10's | S28: Trigger
S29: Skill Crit: On a skill check of 40 or more, add +50% to physical action performance
H30: REQUIERES Master FEAT | R30: Explode | S30: Athletism Item: Specific footwear item can boost athletism
G31: 10 | H31: Skill Check 2k0+5 | N31: Mastery PERK
R33: Martial Temperance | T33: Lv 1 [10]
R34: 1k0+4 | S34: Skill Actions:
S35: ActionMan - perform enhanced physical action such as Running, Jumping, etc. After the action there is a temporal fatigue debuff of 1 dice penalty, stackable
S36: ActionMan II - you can perform a extended Athetism action, until you stop there is no sudden fatigue penalty. Stopping means to have one round where you do not perform athetism actions or you fail your athetism skill check
R37: Check | S37: JumpMan -
R38: 2 | S38: Skill Traits
S39: - Improve 75% of physical action
R40: Raises | S40: - Reduces the amount of Fatigue produced by a Highly physical action
R41: 10's | S41: Trigger
S42: Skill Crit: On a skill check of 40 or more, add +50% to physical action performance
R43: Explode | S43: Athletism Item: Specific footwear item can boost athletism

Sheet BasicSkills
A1: 1 | B1: Athletism | C1: AGI | D1: Support | E1: Root | F1: the simple handling of your body nimbleness including general cardio and gymnastics
A2: 2 | B2: Dismantle | C2: AGI | D2: Support | E2: Root | F2: proficiency into dismantling plants, animals and monsters to extract ingredients and byproducts
A3: 3 | B3: Hide | C3: AGI | D3: Support | E3: Root | F3: the ability to hide efficiently, it only allows to hide without movement
A4: 4 | B4: Riding | C4: AGI | D4: Support | E4: Root | F4: the proficiency into using horses and other similar land riding mounts
A5: 5 | B5: Sleight of Hand | C5: AGI | D5: Support | E5: Root | F5: the use of hand deft movements in cunning ways to peform hand tricks
A6: 6 | B6: Acting | C6: CAR | D6: Support | E6: Root | F6: performing a complete interpretation of a pre-made role/script
A7: 7 | B7: Animal Empathy | C7: CAR | D7: Support | E7: Root | F7: the ability to deal with animals and manage them without the use of force
A8: 8 | B8: Bluff | C8: CAR | D8: Support | E8: Root | F8: proficiency in lying, flattering or gaslighting others in social environments
A9: 9 | B9: Diplomacy | C9: CAR | D9: Support | E9: Root | F9: the ability to mediate or converse in a formal manner in social environments
A10: 10 | B10: Haggle | C10: CAR | D10: Support | E10: Root | F10: the ability to negotiate the trade of goods or advantages in a social environment
A11: 11 | B11: Intimidation | C11: CAR | D11: Support | E11: Root | F11: the ability to threaten others by using simple words and bodily language
A12: 12 | B12: Perform | C12: CAR | D12: Support | E12: Root | F12: the ability to express yourself with body language and produce basic music improvising with sounds
... A55: 55 | B55: Still Mind, Focus | C55: WIL | D55: Core | E55: Root | F55: The main proficiency for self discipline and attaining clarity on combat

Sheet InterSkills
A1: Monster Carver (Basic) | B1: AGI | C1: Support | D1: Dismantle | E1: monster carver is the person who skins and extract every monster part to ensure maximun efficiency and that there is not any loss, unlike a dismantler a carver is capable of dismembering higher ranked monsters with tough skin and poisonous blood until its all usable, however, it needs special tools for diferent monsters
A2: Salvaging (Lesser) | B2: AGI | C2: Support | D2: Dismantle | E2: The skill to reclaim and restore, damaged structures and property without damaging them. In simplified terms allows to extract useful and expensive parts from dificult locations in order to sell or reuse them, also, it is specially important in either magical vessels recovery or a sea ship's recovery of their cargo as only a salvaging expert is capable of recovering sensitive materials in good conditions.
A3: Scavanging | B3: AGI | C3: Support | D3: Dismantle | E3: scavaning is an ability to loot and seek throughly for any usable items in a very efficient manner, the user is like a hound looking everywhere and everything for items to loot, its a skill that increases the both the amount of loot and more
A4: Camoflague (Intermediate) | B4: AGI | C4: Support | D4: Hide | E4: a rare version of hide, which adds the use of natural enviroment coverage to a greater effectivity in adition to hide basic cover qualities, it increases the cover value of a specific natural speciality which choosen upon taken this skill
A5: Cloak and Dagger (Intermediate) | B5: AGI | C5: Support | D5: Hide | E5: the ability to perform acts of questionable nature and hide your trail, the skill is useful to counter investigation skills
A6: Hide in Plain Sight (Basic) | B6: AGI | C6: Support | D6: Hide | E6: the ability to hide in plain sight by blending with the surroundings, this means that instead of hiding by using a cover the user is capable of blending with the active environment by performing actions which are appropiate to fit in with the surroundings, hide in plain sight is greatly influenced by the user outward appereance+C62
A7: Escapist (Inter) | B7: AGI | C7: Support | D7: Sleight of Hand | E7: the skil to escape from binds such as ropes chain or simple grappling
A8: Prestidigitation | B8: AGI | C8: Support | D8: Sleight of Hand | E8: refers to fine motor skills when used by performing artists in different art forms to entertain or manipulate. It is closely associated with close-up magic, card magic, card flourishing and stealing. Because of its heavy use and practice by magicians, sleight of hand is often confused as a branch of magic
A9: Thievery | B9: AGI | C9: Support | D9: Sleight of Hand | E9: The ability to substract elements from a person without his knowledge, its a classic
A10: Beast Trainer | B10: CAR | C10: Support | D10: Animal Empathy | E10: the ability to train beasts of different types, it will increase the INT of the animals and allows the user to teach them tricks
A11: BeastMaster | B11: CAR | C11: Support | D11: Animal Empathy | E11: the ability to manage and control beast creatures, it allows to manage and care for these animals and increases their loyalty to the user
A12: Falconeer | B12: CAR | C12: Support | D12: Animal Empathy | E12: the ability to manage and control flying creatures, it allows to manage and care for these animals and increases their loyalty to the user
... A135: Tower Soldier Technique | B135: STR | C135: Core | D135: Melee Weapons | E135: the techique used by profesional heavy soldiers, who wield large weapons along with heavy armor. This is an entry level skill which uses only non-exotic two handed weapons such as great hammer, great sword, and heavy spear, it offers bonus while using heavy armor
A136: Sprinter | B136: =VLOOKUP(D136,BasicSkills!$B$1:$E$55,2,FALSE) -> AGI | C136: =VLOOKUP(D136,BasicSkills!$B$1:$E$55,3,FALSE) -> Support | D136: Athletism | E136: a skill focusing athletic capacity into sprinting and running
A137: Fitness | B137: =VLOOKUP(D137,BasicSkills!$B$1:$E$55,2,FALSE) -> AGI | C137: =VLOOKUP(D137,BasicSkills!$B$1:$E$55,3,FALSE) -> Support | D137: Athletism | E137: a skill focusing athletic ability into extended fitness and endurance
A138: WarHorse | B138: =VLOOKUP(D138,BasicSkills!$B$1:$E$55,2,FALSE) -> AGI | C138: =VLOOKUP(D138,BasicSkills!$B$1:$E$55,3,FALSE) -> Support | D138: Riding | E138: the skill used to ride high ranking horses such as trained warhorses and similar trained mounts
A139: Equestry | B139: =VLOOKUP(D139,BasicSkills!$B$1:$E$55,2,FALSE) -> AGI | C139: =VLOOKUP(D139,BasicSkills!$B$1:$E$55,3,FALSE) -> Support | D139: Riding | E139: the skill to perform all manners of manuvers while riding a mount
A140: Showman | B140: =VLOOKUP(D140,BasicSkills!$B$1:$E$55,2,FALSE) -> CAR | C140: =VLOOKUP(TRIM(D140),BasicSkills!$B$1:$E$55,3,FALSE) -> Support | D140: Acting | E140: the skill to draw atention and "act" in way that entertains the public
A141: Theatre | B141: =VLOOKUP(D141,BasicSkills!$B$1:$E$55,2,FALSE) -> CAR | C141: =VLOOKUP(D141,BasicSkills!$B$1:$E$55,3,FALSE) -> Support | D141: Acting | E141: the skill to perform acting in a established setting with greater inmersion
A142: Musical Instrument | B142: =VLOOKUP(D142,BasicSkills!$B$1:$E$55,2,FALSE) -> CAR | C142: =VLOOKUP(D142,BasicSkills!$B$1:$E$55,3,FALSE) -> Support | D142: Perform | E142: the skill needed to perform with a musical instrument
A143: Singing | B143: =VLOOKUP(D143,BasicSkills!$B$1:$E$55,2,FALSE) -> CAR | C143: =VLOOKUP(D143,BasicSkills!$B$1:$E$55,3,FALSE) -> Support | D143: Perform | E143: the skill needed to perform with a singing voice, skill does not guarantee the actual voice quality
A144: Dancing | B144: =VLOOKUP(D144,BasicSkills!$B$1:$E$55,2,FALSE) -> CAR | C144: =VLOOKUP(D144,BasicSkills!$B$1:$E$55,3,FALSE) -> Support | D144: Perform | E144: the skill needed to perform using body expression and similar dancing moves
A145: Anomaly Sense | B145: =VLOOKUP(D145,BasicSkills!$B$1:$E$55,2,FALSE) -> CAR | C145: =VLOOKUP(D145,BasicSkills!$B$1:$E$55,3,FALSE) -> Support | D145: Spirit Sensitivity | E145: the skill needed to perceive supernatural begins in a more consise way, still its erratic and cannot "see" spirits
A146: Karmic Bond | B146: =VLOOKUP(D146,BasicSkills!$B$1:$E$55,2,FALSE) -> CAR | C146: =VLOOKUP(D146,BasicSkills!$B$1:$E$55,3,FALSE) -> Support | D146: Spirit Sensitivity | E146: the skill needed to bond with a spirit and feel the bonding in some degree
A147: Metalwork | B147: =VLOOKUP(D147,BasicSkills!$B$1:$E$55,2,FALSE) -> INT | C147: =VLOOKUP(D147,BasicSkills!$B$1:$E$55,3,FALSE) -> Support | D147: Craft | E147: the skill neded to work on metal on a very rudimentary way, similar to making horseshoes or simle cookign utencils
A148: Woodwork | B148: =VLOOKUP(D148,BasicSkills!$B$1:$E$55,2,FALSE) -> INT | C148: =VLOOKUP(D148,BasicSkills!$B$1:$E$55,3,FALSE) -> Support | D148: Craft | E148: the skill neded to work on wood on a rough way, good for making simple furniture and basic wood tools
A149: Gumption | B149: =VLOOKUP(D149,BasicSkills!$B$1:$E$55,2,FALSE) -> INT | C149: =VLOOKUP(D149,BasicSkills!$B$1:$E$55,3,FALSE) -> Support | D149: Culture Lore | E149: the skill to understand the way people think within a certain zone, it allows you use local customs and prejudices to your advantage
A150: Folklore | B150: =VLOOKUP(D150,BasicSkills!$B$1:$E$55,2,FALSE) -> INT | C150: =VLOOKUP(D150,BasicSkills!$B$1:$E$55,3,FALSE) -> Support | D150: Culture Lore | E150: the lore of the folk, it lets you understand the common knowledge shared among the locals in a zone including their myths and trends
A151: Repairs | B151: =VLOOKUP(D151,BasicSkills!$B$1:$E$55,2,FALSE) -> INT | C151: =VLOOKUP(D151,BasicSkills!$B$1:$E$55,3,FALSE) -> Support | D151: Mechanics | E151: the skill to repair mechanical items, but it cannot repair destroyed ones
A152: Mechanic Operation | B152: =VLOOKUP(D152,BasicSkills!$B$1:$E$55,2,FALSE) -> INT | C152: =VLOOKUP(D152,BasicSkills!$B$1:$E$55,3,FALSE) -> Support | D152: Mechanics | E152: the skill needed to operate mechanical devises such as vehicles or simple machines
... A181: Pathfinder | B181: =VLOOKUP(D181,BasicSkills!$B$1:$E$55,2,FALSE) -> WIL | C181: =VLOOKUP(D181,BasicSkills!$B$1:$E$55,3,FALSE) -> Support | D181: Wayfarer | E181: a skill focused on finding lost paths in treacherous roads

Sheet GroupvsSkills
A1: ACADEMIC | B1: Investigation | C1: PER
A2: ACADEMIC | B2: Knowledge (Specific) | C2: INT
A3: ACADEMIC | B3: Linguistics | C3: INT
A4: ARTISAN | B4: Apraisal | C4: PER
A5: ARTISAN | B5: Craft | C5: INT
A6: ARTISAN | B6: Minning | C6: STR
A7: BARD | B7: Diplomacy | C7: CAR
A8: BARD | B8: Mana Sensitivity | C8: WIL
A9: BARD | B9: Melee Weapons Handling | C9: STR
A10: BARD | B10: Perform | C10: CAR
A11: BARD | B11: Sleight of Hand | C11: AGI
A12: BRAWLER | B12: Athletism | C12: AGI
... A100: WITCH | B100: Spirit Sensitivity | C100: CAR

Sheet SkillGroup
A1: ACADEMIC | B1: SUPPORT | C1: INT
A2: ARTISAN | B2: SUPPORT | C2: INT
A3: BUTCHER | B3: SUPPORT | C3: STR
A4: ENGINEER | B4: SUPPORT | C4: INT
A5: FARMER | B5: SUPPORT | C5: WIL
A6: HIGH CLASS | B6: SUPPORT | C6: CHA
A7: HUNTER | B7: SUPPORT | C7: PER
A8: LAWMAKER | B8: SUPPORT | C8: WIL
A9: LOW CLASS | B9: SUPPORT | C9: PER
A10: MERC | B10: SUPPORT | C10: STR
A11: MERCHANT | B11: SUPPORT | C11: PER
A12: MINSTREL | B12: SUPPORT | C12: PER
... A28: WARRIOR | B28: CORE | C28: STR

Sheet Sheet6
A1: - Basic Array Mastery | D1: Formal Magics 8 | I1: =MID(A1,4,LEN(A1)) -> Basic Array Mastery | J1: =VLOOKUP(MID(D1,1,LEN(D1)-2),BasicSkills!$B$1:$E$55,2,FALSE) -> INT | K1: =VLOOKUP(MID(D1,1,LEN(D1)-2),BasicSkills!$B$1:$E$55,3,FALSE) -> Support | L1: =TRIM(MID(D1,1,LEN(D1)-2)) -> Formal Magics | M1: =A2 -> the ability to peform basic arrays, allowing a wide range of applications in magic based cultures, including the making of semi-permanent magic circles
A2: the ability to peform basic arrays, allowing a wide range of applications in magic based cultures, including the making of semi-permanent magic circles
A3: - Witchcraft | D3: Formal Magics 7 | I3: =MID(A3,4,LEN(A3)) -> Witchcraft | J3: =VLOOKUP(MID(D3,1,LEN(D3)-2),BasicSkills!$B$1:$E$55,2,FALSE) -> INT | K3: =VLOOKUP(MID(D3,1,LEN(D3)-2),BasicSkills!$B$1:$E$55,3,FALSE) -> Support | L3: =TRIM(MID(D3,1,LEN(D3)-2)) -> Formal Magics | M3: =A4 -> The ancient art of witchcraft as explained by the kabbalistic witches of the modern era, its rich in occult knowledge relating to nature and magic
A4: The ancient art of witchcraft as explained by the kabbalistic witches of the modern era, its rich in occult knowledge relating to nature and magic
A5: - Basic Magic Theory | D5: Spellcraft 9 | I5: =MID(A5,4,LEN(A5)) -> Basic Magic Theory | J5: =VLOOKUP(MID(D5,1,LEN(D5)-2),BasicSkills!$B$1:$E$55,2,FALSE) -> PER | K5: =VLOOKUP(MID(D5,1,LEN(D5)-2),BasicSkills!$B$1:$E$55,3,FALSE) -> Support | L5: =TRIM(MID(D5,1,LEN(D5)-2)) -> Spellcraft | M5: =A6 -> the ability to study, disect and understand magic, its a rather technical skill used to obtain understanding magic and the laws of the world
A6: the ability to study, disect and understand magic, its a rather technical skill used to obtain understanding magic and the laws of the world
A7: - SpellBreaker | D7: Spellcraft 8 | I7: =MID(A7,4,LEN(A7)) -> SpellBreaker | J7: =VLOOKUP(MID(D7,1,LEN(D7)-2),BasicSkills!$B$1:$E$55,2,FALSE) -> PER | K7: =VLOOKUP(MID(D7,1,LEN(D7)-2),BasicSkills!$B$1:$E$55,3,FALSE) -> Support | L7: =TRIM(MID(D7,1,LEN(D7)-2)) -> Spellcraft | M7: =A8 -> the ability to break magic apart by understanding its estructure and composition, this specialized skill would allow a non-mage to counter magic using basic physical components
A8: the ability to break magic apart by understanding its estructure and composition, this specialized skill would allow a non-mage to counter magic using basic physical components
A9: - Battlecraft | D9: Spellcraft 7 | I9: =MID(A9,4,LEN(A9)) -> Battlecraft | J9: =VLOOKUP(MID(D9,1,LEN(D9)-2),BasicSkills!$B$1:$E$55,2,FALSE) -> PER | K9: =VLOOKUP(MID(D9,1,LEN(D9)-2),BasicSkills!$B$1:$E$55,3,FALSE) -> Support | L9: =TRIM(MID(D9,1,LEN(D9)-2)) -> Spellcraft | M9: =A10 -> the ability to use and apply magic during battle in a efficient manner, it makes the casting of magic more efficient by adjusting the user to chaotic enviroments, its a nesesary skill for mage knights
A10: the ability to use and apply magic during battle in a efficient manner, it makes the casting of magic more efficient by adjusting the user to chaotic enviroments, its a nesesary skill for mage knights
A11: - Fate Walker | D11: Astrology 9 | I11: =MID(A11,4,LEN(A11)) -> Fate Walker | J11: =VLOOKUP(MID(D11,1,LEN(D11)-2),BasicSkills!$B$1:$E$55,2,FALSE) -> INT | K11: =VLOOKUP(MID(D11,1,LEN(D11)-2),BasicSkills!$B$1:$E$55,3,FALSE) -> Support | L11: =TRIM(MID(D11,1,LEN(D11)-2)) -> Astrology | M11: =A12 -> the ability to follow fate and let yourself go with the current of destiny, you are a awakening as a seer and fate is showing you visions and dreams
A12: the ability to follow fate and let yourself go with the current of destiny, you are a awakening as a seer and fate is showing you visions and dreams
A13: - Occultism | D13: Astrology 8 | I13: =MID(A13,4,LEN(A13)) -> Occultism | J13: =VLOOKUP(MID(D13,1,LEN(D13)-2),BasicSkills!$B$1:$E$55,2,FALSE) -> INT | K13: =VLOOKUP(MID(D13,1,LEN(D13)-2),BasicSkills!$B$1:$E$55,3,FALSE) -> Support | L13: =TRIM(MID(D13,1,LEN(D13)-2)) -> Astrology | M13: =A14 -> The user recognizes occult paraphernalia, words, and concepts, and identifies grimoires of magic and occult codes when he sees them. This is the skill that dives deep into superstision and obscure esoteric knowledge, some of it is bullshit some of it is the gate to the abyss
A14: The user recognizes occult paraphernalia, words, and concepts, and identifies grimoires of magic and occult codes when he sees them. This is the skill that dives deep into superstision and obscure esoteric knowledge, some of it is bullshit some of it is the gate to the abyss
A15: - Fortune-Telling | D15: Astrology 7 | I15: =MID(A15,4,LEN(A15)) -> Fortune-Telling | J15: =VLOOKUP(MID(D15,1,LEN(D15)-2),BasicSkills!$B$1:$E$55,2,FALSE) -> INT | K15: =VLOOKUP(MID(D15,1,LEN(D15)-2),BasicSkills!$B$1:$E$55,3,FALSE) -> Support | L15: =TRIM(MID(D15,1,LEN(D15)-2)) -> Astrology | M15: =A16 -> the ability to glimpse the strands of fate and destiny that make up the universe, and can gain some glimmer of insight into the future as a result
A16: the ability to glimpse the strands of fate and destiny that make up the universe, and can gain some glimmer of insight into the future as a result
A17: - Inhuman Linguistics | D17: Linguistics 9 | I17: =MID(A17,4,LEN(A17)) -> Inhuman Linguistics | J17: =VLOOKUP(MID(D17,1,LEN(D17)-2),BasicSkills!$B$1:$E$55,2,FALSE) -> INT | K17: =VLOOKUP(MID(D17,1,LEN(D17)-2),BasicSkills!$B$1:$E$55,3,FALSE) -> Support | L17: =TRIM(MID(D17,1,LEN(D17)-2)) -> Linguistics | M17: =A18 -> the ability to translate ancient and lost languages provided that you have sufficient material to produce a codex. Otherwise, it also can generate a simplified codex of a language using enought data
A18: the ability to translate ancient and lost languages provided that you have sufficient material to produce a codex. Otherwise, it also can generate a simplified codex of a language using enought data
A19: - Encoding | D19: Linguistics 8 | I19: =MID(A19,4,LEN(A19)) -> Encoding | J19: =VLOOKUP(MID(D19,1,LEN(D19)-2),BasicSkills!$B$1:$E$55,2,FALSE) -> INT | K19: =VLOOKUP(MID(D19,1,LEN(D19)-2),BasicSkills!$B$1:$E$55,3,FALSE) -> Support | L19: =TRIM(MID(D19,1,LEN(D19)-2)) -> Linguistics | M19: =A20 -> the ability to cipher, decipher and compress data into encoded messages, its a highly sought knowledge since most magical messages must be coded in someway. Its possible to create a cipher codex in order to create simplified cipher for common people
A20: the ability to cipher, decipher and compress data into encoded messages, its a highly sought knowledge since most magical messages must be coded in someway. Its possible to create a cipher codex in order to create simplified cipher for common people
A21: - Caligraphy | D21: Linguistics 7 | I21: =MID(A21,4,LEN(A21)) -> Caligraphy | J21: =VLOOKUP(MID(D21,1,LEN(D21)-2),BasicSkills!$B$1:$E$55,2,FALSE) -> INT | K21: =VLOOKUP(MID(D21,1,LEN(D21)-2),BasicSkills!$B$1:$E$55,3,FALSE) -> Support | L21: =TRIM(MID(D21,1,LEN(D21)-2)) -> Linguistics | M21: =A22 -> Calligraphy is considered an art form by many, but it can be used in many ways as a means to deliver messages or as way to gain enlightment
A22: Calligraphy is considered an art form by many, but it can be used in many ways as a means to deliver messages or as way to gain enlightment
A23: - Basic Schoolastic Mastery | D23: Knowledge 9 | I23: =MID(A23,4,LEN(A23)) -> Basic Schoolastic Mastery | J23: =VLOOKUP(MID(D23,1,LEN(D23)-2),BasicSkills!$B$1:$E$55,2,FALSE) -> INT | K23: =VLOOKUP(MID(D23,1,LEN(D23)-2),BasicSkills!$B$1:$E$55,3,FALSE) -> Support | L23: =TRIM(MID(D23,1,LEN(D23)-2)) -> Knowledge | M23: =A24 -> The ability to research a wide variety of knowledges related to the parent knowledge, this is a ever growing skill, the more knowledge you posess the bigger its influence
A24: The ability to research a wide variety of knowledges related to the parent knowledge, this is a ever growing skill, the more knowledge you posess the bigger its influence
A25: - High Knowledge | D25: Knowledge 8 | I25: =MID(A25,4,LEN(A25)) -> High Knowledge | J25: =VLOOKUP(MID(D25,1,LEN(D25)-2),BasicSkills!$B$1:$E$55,2,FALSE) -> INT | K25: =VLOOKUP(MID(D25,1,LEN(D25)-2),BasicSkills!$B$1:$E$55,3,FALSE) -> Support | L25: =TRIM(MID(D25,1,LEN(D25)-2)) -> Knowledge | M25: =A26 -> The ability access a particular branch of a parent knowledge, unlike the parent knowledge which is rather generalistic this is a specific form of knowlege much more focused and much more detailed about a particular subject
A26: The ability access a particular branch of a parent knowledge, unlike the parent knowledge which is rather generalistic this is a specific form of knowlege much more focused and much more detailed about a particular subject
A27: - Basic Philosophy | D27: Knowledge 7 | I27: =MID(A27,4,LEN(A27)) -> Basic Philosophy | J27: =VLOOKUP(MID(D27,1,LEN(D27)-2),BasicSkills!$B$1:$E$55,2,FALSE) -> INT | K27: =VLOOKUP(MID(D27,1,LEN(D27)-2),BasicSkills!$B$1:$E$55,3,FALSE) -> Support | L27: =TRIM(MID(D27,1,LEN(D27)-2)) -> Knowledge | M27: =A28 -> A learned person is capable of understanding the concept of things and the ethereal behind the physical
A28: A learned person is capable of understanding the concept of things and the ethereal behind the physical
A29: - Encyclopedia | D29: Knowledge 7 | I29: =MID(A29,4,LEN(A29)) -> Encyclopedia | J29: =VLOOKUP(MID(D29,1,LEN(D29)-2),BasicSkills!$B$1:$E$55,2,FALSE) -> INT | K29: =VLOOKUP(MID(D29,1,LEN(D29)-2),BasicSkills!$B$1:$E$55,3,FALSE) -> Support | L29: =TRIM(MID(D29,1,LEN(D29)-2)) -> Knowledge | M29: =A30 -> a simple generalized knowledge focused on knowing about the definition of a lot of things, its useful when traveling and has a large syngergy with appraisal skill
A30: a simple generalized knowledge focused on knowing about the definition of a lot of things, its useful when traveling and has a large syngergy with appraisal skill
A31: - Lesser Enigma | D31: Investigation 9 | I31: =MID(A31,4,LEN(A31)) -> Lesser Enigma | J31: =VLOOKUP(MID(D31,1,LEN(D31)-2),BasicSkills!$B$1:$E$55,2,FALSE) -> PER | K31: =VLOOKUP(MID(D31,1,LEN(D31)-2),BasicSkills!$B$1:$E$55,3,FALSE) -> Support | L31: =TRIM(MID(D31,1,LEN(D31)-2)) -> Investigation | M31: =A32 -> Logic problems, puzzles and mysteries are all in the realm of Enigmas. Characters with this talent link information and hunches together to solve conundrums of all varieties, from the spiritual to the material
A32: Logic problems, puzzles and mysteries are all in the realm of Enigmas. Characters with this talent link information and hunches together to solve conundrums of all varieties, from the spiritual to the material
A33: - Sleuth | D33: Investigation 8 | I33: =MID(A33,4,LEN(A33)) -> Sleuth | J33: =VLOOKUP(MID(D33,1,LEN(D33)-2),BasicSkills!$B$1:$E$55,2,FALSE) -> PER | K33: =VLOOKUP(MID(D33,1,LEN(D33)-2),BasicSkills!$B$1:$E$55,3,FALSE) -> Support | L33: =TRIM(MID(D33,1,LEN(D33)-2)) -> Investigation | M33: =A34 -> The development of atention to fine details as well as logical deductions, its a skill used to make sharp remaks and perceive details which easily escape the common man. You've learned to notice details others might overlook, and might make an admirable detective. This knowledge represents not only a good eye for detail, but also an ability to do research and follow leads
A34: The development of atention to fine details as well as logical deductions, its a skill used to make sharp remaks and perceive details which easily escape the common man. You've learned to notice details others might overlook, and might make an admirable detective. This knowledge represents not only a good eye for detail, but also an ability to do research and follow leads
A35: - Interrogation | D35: Investigation 7 | I35: =MID(A35,4,LEN(A35)) -> Interrogation | J35: =VLOOKUP(MID(D35,1,LEN(D35)-2),BasicSkills!$B$1:$E$55,2,FALSE) -> PER | K35: =VLOOKUP(MID(D35,1,LEN(D35)-2),BasicSkills!$B$1:$E$55,3,FALSE) -> Support | L35: =TRIM(MID(D35,1,LEN(D35)-2)) -> Investigation | M35: =A36 -> the ability to extract information from a target using you observation power along with your skill in order break away lies and deceit
A36: the ability to extract information from a target using you observation power along with your skill in order break away lies and deceit
A37: - Lesser Counceling | D37: Sense Motive 9 | I37: =MID(A37,4,LEN(A37)) -> Lesser Counceling | J37: =VLOOKUP(MID(D37,1,LEN(D37)-2),BasicSkills!$B$1:$E$55,2,FALSE) -> PER | K37: =VLOOKUP(MID(D37,1,LEN(D37)-2),BasicSkills!$B$1:$E$55,3,FALSE) -> Support | L37: =TRIM(MID(D37,1,LEN(D37)-2)) -> Sense Motive | M37: =A38 -> You are skilled in helping with mental stress and treating simple mental ailments (such as Derangements) without resorting to the use of behavior-altering drugs
A38: You are skilled in helping with mental stress and treating simple mental ailments (such as Derangements) without resorting to the use of behavior-altering drugs
A39: - Empathic Insight | D39: Sense Motive 8 | I39: =MID(A39,4,LEN(A39)) -> Empathic Insight | J39: =VLOOKUP(MID(D39,1,LEN(D39)-2),BasicSkills!$B$1:$E$55,2,FALSE) -> PER | K39: =VLOOKUP(MID(D39,1,LEN(D39)-2),BasicSkills!$B$1:$E$55,3,FALSE) -> Support | L39: =TRIM(MID(D39,1,LEN(D39)-2)) -> Sense Motive | M39: =A40 -> You understand the emotions of others, and can sympathize with, feign sympathy for, or play on such emotions as you see fit. You are an easy hand at discerning motive, and might be able to pick up on when someone's lying to you. However, you may be so in tune with other people's feelings that your own emotions are affected
A40: You understand the emotions of others, and can sympathize with, feign sympathy for, or play on such emotions as you see fit. You are an easy hand at discerning motive, and might be able to pick up on when someone's lying to you. However, you may be so in tune with other people's feelings that your own emotions are affected
A41: - Judgement (Person) | D41: Sense Motive 7 | I41: =MID(A41,4,LEN(A41)) -> Judgement (Person) | J41: =VLOOKUP(MID(D41,1,LEN(D41)-2),BasicSkills!$B$1:$E$55,2,FALSE) -> PER | K41: =VLOOKUP(MID(D41,1,LEN(D41)-2),BasicSkills!$B$1:$E$55,3,FALSE) -> Support | L41: =TRIM(MID(D41,1,LEN(D41)-2)) -> Sense Motive | M41: =A42 -> you have developed the ability to know instinctively when people are not telling you the truth or not telling you the whole truth. There is a way they look, a tone of voice, a movement of the eyes - you can’t analyze it, but it’s always there and your instincts rarely let you down.
A42: you have developed the ability to know instinctively when people are not telling you the truth or not telling you the whole truth. There is a way they look, a tone of voice, a movement of the eyes - you can’t analyze it, but it’s always there and your instincts rarely let you down.
A43: - Dignity | D43: Diplomacy 9 | I43: =MID(A43,4,LEN(A43)) -> Dignity | J43: =VLOOKUP(MID(D43,1,LEN(D43)-2),BasicSkills!$B$1:$E$55,2,FALSE) -> CAR | K43: =VLOOKUP(MID(D43,1,LEN(D43)-2),BasicSkills!$B$1:$E$55,3,FALSE) -> Support | L43: =TRIM(MID(D43,1,LEN(D43)-2)) -> Diplomacy | M43: =A44 -> little words are needed, a person with tremendous dignity is someone who can project a charming and confident self, its a basic skills to leaders and lords
A44: little words are needed, a person with tremendous dignity is someone who can project a charming and confident self, its a basic skills to leaders and lords
A45: - Basic Conversation | D45: Diplomacy 8 | I45: =MID(A45,4,LEN(A45)) -> Basic Conversation | J45: =VLOOKUP(MID(D45,1,LEN(D45)-2),BasicSkills!$B$1:$E$55,2,FALSE) -> CAR | K45: =VLOOKUP(MID(D45,1,LEN(D45)-2),BasicSkills!$B$1:$E$55,3,FALSE) -> Support | L45: =TRIM(MID(D45,1,LEN(D45)-2)) -> Diplomacy | M45: =A46 -> the ability to establish a pleasant exchange in a festive enviroment, conversation is a high class hobby of most nobbles and usually it entails long dinners, with storytelling and good wit and sharing, its important to gain friends in high society
A46: the ability to establish a pleasant exchange in a festive enviroment, conversation is a high class hobby of most nobbles and usually it entails long dinners, with storytelling and good wit and sharing, its important to gain friends in high society
A47: - Burocracy | D47: Diplomacy 7 | I47: =MID(A47,4,LEN(A47)) -> Burocracy | J47: =VLOOKUP(MID(D47,1,LEN(D47)-2),BasicSkills!$B$1:$E$55,2,FALSE) -> CAR | K47: =VLOOKUP(MID(D47,1,LEN(D47)-2),BasicSkills!$B$1:$E$55,3,FALSE) -> Support | L47: =TRIM(MID(D47,1,LEN(D47)-2)) -> Diplomacy | M47: =A48 -> the ability to work in a efficient manner in the a company or state buroucracy
A48: the ability to work in a efficient manner in the a company or state buroucracy
A49: - Informant | D49: Streetwise 9 | I49: =MID(A49,4,LEN(A49)) -> Informant | J49: =VLOOKUP(MID(D49,1,LEN(D49)-2),BasicSkills!$B$1:$E$55,2,FALSE) -> PER | K49: =VLOOKUP(MID(D49,1,LEN(D49)-2),BasicSkills!$B$1:$E$55,3,FALSE) -> Support | L49: =TRIM(MID(D49,1,LEN(D49)-2)) -> Streetwise | M49: =A50 -> the ability to gather high class information and rummors, the user will be a able to quickly obtain news and details of happenings in a city scale region
A50: the ability to gather high class information and rummors, the user will be a able to quickly obtain news and details of happenings in a city scale region
A51: - Underworld | D51: Streetwise 8 | I51: =MID(A51,4,LEN(A51)) -> Underworld | J51: =VLOOKUP(MID(D51,1,LEN(D51)-2),BasicSkills!$B$1:$E$55,2,FALSE) -> PER | K51: =VLOOKUP(MID(D51,1,LEN(D51)-2),BasicSkills!$B$1:$E$55,3,FALSE) -> Support | L51: =TRIM(MID(D51,1,LEN(D51)-2)) -> Streetwise | M51: =A52 -> the ability to blend into the underworld, you can claim to be part of any gang or organized crime as long as you make some info gathering first
A52: the ability to blend into the underworld, you can claim to be part of any gang or organized crime as long as you make some info gathering first
A53: - Broker | D53: Streetwise 7 | I53: =MID(A53,4,LEN(A53)) -> Broker | J53: =VLOOKUP(MID(D53,1,LEN(D53)-2),BasicSkills!$B$1:$E$55,2,FALSE) -> PER | K53: =VLOOKUP(MID(D53,1,LEN(D53)-2),BasicSkills!$B$1:$E$55,3,FALSE) -> Support | L53: =TRIM(MID(D53,1,LEN(D53)-2)) -> Streetwise | M53: =A54 -> the ability to obtain assets from the street in a informal manner, you can buy drugs, illegal o forbidden materials or obtain vital information but everything has a price. Unlike "black market" this skill operates in the informal exchanges rather than organized transaction
A54: the ability to obtain assets from the street in a informal manner, you can buy drugs, illegal o forbidden materials or obtain vital information but everything has a price. Unlike "black market" this skill operates in the informal exchanges rather than organized transaction
A55: - Masquerade | D55: Bluff 9 | I55: =MID(A55,4,LEN(A55)) -> Masquerade | J55: =VLOOKUP(MID(D55,1,LEN(D55)-2),BasicSkills!$B$1:$E$55,2,FALSE) -> CAR | K55: =VLOOKUP(MID(D55,1,LEN(D55)-2),BasicSkills!$B$1:$E$55,3,FALSE) -> Support | L55: =TRIM(MID(D55,1,LEN(D55)-2)) -> Bluff | M55: =A56 -> Some people live two lives, one in the light with a public profile and other in the shadows, this is the ability to create a double life allowing the player to separate both and never be suspected
A56: Some people live two lives, one in the light with a public profile and other in the shadows, this is the ability to create a double life allowing the player to separate both and never be suspected
A57: - Subterfuge | D57: Bluff 8 | I57: =MID(A57,4,LEN(A57)) -> Subterfuge | J57: =VLOOKUP(MID(D57,1,LEN(D57)-2),BasicSkills!$B$1:$E$55,2,FALSE) -> CAR | K57: =VLOOKUP(MID(D57,1,LEN(D57)-2),BasicSkills!$B$1:$E$55,3,FALSE) -> Support | L57: =TRIM(MID(D57,1,LEN(D57)-2)) -> Bluff | M57: =A58 -> You know how to conceal your own motives and project what you like. Furthermore, you can root out other people's motives, then use those motives against them
A58: You know how to conceal your own motives and project what you like. Furthermore, you can root out other people's motives, then use those motives against them
A59: - Fawn | D59: Bluff 7 | I59: =MID(A59,4,LEN(A59)) -> Fawn | J59: =VLOOKUP(MID(D59,1,LEN(D59)-2),BasicSkills!$B$1:$E$55,2,FALSE) -> CAR | K59: =VLOOKUP(MID(D59,1,LEN(D59)-2),BasicSkills!$B$1:$E$55,3,FALSE) -> Support | L59: =TRIM(MID(D59,1,LEN(D59)-2)) -> Bluff | M59: =A60 -> the ability to adulate and curry into favor from people using sweet words and correct language, its imperative as a street etiquette for survival of the weak, it is limited to etiquettes known by the user. By spending time you can easily built a good relationship with most NPC. Fawn is seen as a despicable act by the more honorable or disciplined people, so be careful
A60: the ability to adulate and curry into favor from people using sweet words and correct language, its imperative as a street etiquette for survival of the weak, it is limited to etiquettes known by the user. By spending time you can easily built a good relationship with most NPC. Fawn is seen as a despicable act by the more honorable or disciplined people, so be careful
A61: Negociator (Basic) | D61: Haggle 9 | I61: =A61 -> Negociator (Basic) | J61: =VLOOKUP(MID(D61,1,LEN(D61)-2),BasicSkills!$B$1:$E$55,2,FALSE) -> CAR | K61: =VLOOKUP(MID(D61,1,LEN(D61)-2),BasicSkills!$B$1:$E$55,3,FALSE) -> Support | L61: =TRIM(MID(D61,1,LEN(D61)-2)) -> Haggle | M61: =A62 -> Negociator is the ability to use your haggling skills to negotiate and mediate in most instances, You're a deal maker, you make a living in through negotiating difficult trade. Whatever your background you are an expert at the art of negotiations. Either born with a silvered tong or forged skills through a teacher and experience, you have an uncanny ability to find the best deal no matter the situation
A62: Negociator is the ability to use your haggling skills to negotiate and mediate in most instances, You're a deal maker, you make a living in through negotiating difficult trade. Whatever your background you are an expert at the art of negotiations. Either born with a silvered tong or forged skills through a teacher and experience, you have an uncanny ability to find the best deal no matter the situation
A63: Swindler | D63: Haggle 8 | I63: =A63 -> Swindler | J63: =VLOOKUP(MID(D63,1,LEN(D63)-2),BasicSkills!$B$1:$E$55,2,FALSE) -> CAR | K63: =VLOOKUP(MID(D63,1,LEN(D63)-2),BasicSkills!$B$1:$E$55,3,FALSE) -> Support | L63: =TRIM(MID(D63,1,LEN(D63)-2)) -> Haggle | M63: =A64 -> A swindler, is adept into making people buy low quality items and trash for excessive amounts, they are regarded poorly by the merchant community but they still make a fair bit of dough. Also character capable of buying and selling item illegal items and substances, he knows who and where to buy and can sell small illegal goods in a few hours of work.
A64: A swindler, is adept into making people buy low quality items and trash for excessive amounts, they are regarded poorly by the merchant community but they still make a fair bit of dough. Also character capable of buying and selling item illegal items and substances, he knows who and where to buy and can sell small illegal goods in a few hours of work.
A65: Salesman | D65: Haggle 7 | I65: =A65 -> Salesman | J65: =VLOOKUP(MID(D65,1,LEN(D65)-2),BasicSkills!$B$1:$E$55,2,FALSE) -> CAR | K65: =VLOOKUP(MID(D65,1,LEN(D65)-2),BasicSkills!$B$1:$E$55,3,FALSE) -> Support | L65: =TRIM(MID(D65,1,LEN(D65)-2)) -> Haggle | M65: =A66 -> Salesman is the skill which embodies the art of performing advances on unsuspecting people in order to offer services and productos for purchases, its really efficient to break the first barriers onto most people, but its useless with hostile targets, however, salesmen build trust upon each and every sale so their customers become sort or less their own personal network.
A66: Salesman is the skill which embodies the art of performing advances on unsuspecting people in order to offer services and productos for purchases, its really efficient to break the first barriers onto most people, but its useless with hostile targets, however, salesmen build trust upon each and every sale so their customers become sort or less their own personal network.
A67: Lesser Anti-Forgery | D67: Appraisal 9 | I67: =A67 -> Lesser Anti-Forgery | J67: =VLOOKUP(MID(D67,1,LEN(D67)-2),BasicSkills!$B$1:$E$55,2,FALSE) -> PER | K67: =VLOOKUP(MID(D67,1,LEN(D67)-2),BasicSkills!$B$1:$E$55,3,FALSE) -> Support | L67: =TRIM(MID(D67,1,LEN(D67)-2)) -> Appraisal | M67: =A68 -> The ability to see throught fake items and similar counterfeit elements such as counterfeit money, smuggled items and similar items trying to pass as normal while beign imitations or fake.
A68: The ability to see throught fake items and similar counterfeit elements such as counterfeit money, smuggled items and similar items trying to pass as normal while beign imitations or fake.
A69: Human Assessment | D69: Appraisal 8 | I69: =A69 -> Human Assessment | J69: =VLOOKUP(MID(D69,1,LEN(D69)-2),BasicSkills!$B$1:$E$55,2,FALSE) -> PER | K69: =VLOOKUP(MID(D69,1,LEN(D69)-2),BasicSkills!$B$1:$E$55,3,FALSE) -> Support | L69: =TRIM(MID(D69,1,LEN(D69)-2)) -> Appraisal | M69: =A70 -> The ability to appraise humanoid qualities on a target, it is used mostly by slavers and slave comerce in order to determine the "quality" of a humanoid target. The skill provides extra information such as a physical conditions, underlying medical details, and any superficial information.
A70: The ability to appraise humanoid qualities on a target, it is used mostly by slavers and slave comerce in order to determine the "quality" of a humanoid target. The skill provides extra information such as a physical conditions, underlying medical details, and any superficial information.
A71: Judgment (Item) | D71: Appraisal 7 | I71: =A71 -> Judgment (Item) | J71: =VLOOKUP(MID(D71,1,LEN(D71)-2),BasicSkills!$B$1:$E$55,2,FALSE) -> PER | K71: =VLOOKUP(MID(D71,1,LEN(D71)-2),BasicSkills!$B$1:$E$55,3,FALSE) -> Support | L71: =TRIM(MID(D71,1,LEN(D71)-2)) -> Appraisal | M71: =A72 -> The ability to understand items and products and class them into ranks and levels, it allows the user to understand items highlights and downsides of an item, moreover, a raise will allow the user to learn about the item from the market perspective such as rumors and basic superficial lore. It can be used to uncover an items basic abilties and passives, higher levels of the skill allow the user to know more
A72: The ability to understand items and products and class them into ranks and levels, it allows the user to understand items highlights and downsides of an item, moreover, a raise will allow the user to learn about the item from the market perspective such as rumors and basic superficial lore. It can be used to uncover an items basic abilties and passives, higher levels of the skill allow the user to know more
A73: Barbarian Vandal Technique | D73: Melee Weapons Lv 8 | I73: =A73 -> Barbarian Vandal Technique | J73: =VLOOKUP(MID(D73,1,LEN(D73)-5),BasicSkills!$B$1:$E$55,2,FALSE) -> STR | K73: =VLOOKUP(MID(D73,1,LEN(D73)-5),BasicSkills!$B$1:$E$55,3,FALSE) -> Core | L73: =TRIM(MID(D73,1,LEN(D73)-5)) -> Melee Weapons | M73: =A74 -> the technique used by barbarians in battle where the use of armor is sacrificed for higher movility while using either Great blades, Great Axes or Great maces. It offers bonus while not using any armor or battle cloth armor
A74: the technique used by barbarians in battle where the use of armor is sacrificed for higher movility while using either Great blades, Great Axes or Great maces. It offers bonus while not using any armor or battle cloth armor
A75: Tower Soldier Technique | D75: Melee Weapons Lv 8 | I75: =A75 -> Tower Soldier Technique | J75: =VLOOKUP(MID(D75,1,LEN(D75)-5),BasicSkills!$B$1:$E$55,2,FALSE) -> STR | K75: =VLOOKUP(MID(D75,1,LEN(D75)-5),BasicSkills!$B$1:$E$55,3,FALSE) -> Core | L75: =TRIM(MID(D75,1,LEN(D75)-5)) -> Melee Weapons | M75: =A76 -> the techique used by profesional heavy soldiers, who wield large weapons along with heavy armor. This is an entry level skill which uses only non-exotic two handed weapons such as great hammer, great sword, and heavy spear, it offers bonus while using heavy armor
A76: the techique used by profesional heavy soldiers, who wield large weapons along with heavy armor. This is an entry level skill which uses only non-exotic two handed weapons such as great hammer, great sword, and heavy spear, it offers bonus while using heavy armor
A77: Heavy Blade Technique | D77: Melee Weapons Lv 7 | I77: =A77 -> Heavy Blade Technique | J77: =VLOOKUP(MID(D77,1,LEN(D77)-5),BasicSkills!$B$1:$E$55,2,FALSE) -> STR | K77: =VLOOKUP(MID(D77,1,LEN(D77)-5),BasicSkills!$B$1:$E$55,3,FALSE) -> Core | L77: =TRIM(MID(D77,1,LEN(D77)-5)) -> Melee Weapons | M77: =A78 -> The specialized use of heavy sword type weapons both in one hand and two hand forms, however, only heavy swords can be used with this technique
A78: The specialized use of heavy sword type weapons both in one hand and two hand forms, however, only heavy swords can be used with this technique
A79: Heavy Spear Technique | D79: Melee Weapons Lv 7 | I79: =A79 -> Heavy Spear Technique | J79: =VLOOKUP(MID(D79,1,LEN(D79)-5),BasicSkills!$B$1:$E$55,2,FALSE) -> STR | K79: =VLOOKUP(MID(D79,1,LEN(D79)-5),BasicSkills!$B$1:$E$55,3,FALSE) -> Core | L79: =TRIM(MID(D79,1,LEN(D79)-5)) -> Melee Weapons | M79: =A80 -> The specialized use of heavy spears type weapons both in one hand and two hand forms, however, only heavy spears can be used with this technique
A80: The specialized use of heavy spears type weapons both in one hand and two hand forms, however, only heavy spears can be used with this technique
A81: Axeman Technique | D81: Melee Weapons Lv 7 | I81: =A81 -> Axeman Technique | J81: =VLOOKUP(MID(D81,1,LEN(D81)-5),BasicSkills!$B$1:$E$55,2,FALSE) -> STR | K81: =VLOOKUP(MID(D81,1,LEN(D81)-5),BasicSkills!$B$1:$E$55,3,FALSE) -> Core | L81: =TRIM(MID(D81,1,LEN(D81)-5)) -> Melee Weapons | M81: =A82 -> The specialized use of heavy axe type weapons both in one hand and two hand forms, however, only heavy axes can be used with this technique
A82: The specialized use of heavy axe type weapons both in one hand and two hand forms, however, only heavy axes can be used with this technique
A83: Basic "Bear Guardian" Combat Method | D83: Heavy Armor Lv 9 | I83: =A83 -> Basic "Bear Guardian" Combat Method | J83: =VLOOKUP(MID(D83,1,LEN(D83)-5),BasicSkills!$B$1:$E$55,2,FALSE) -> STR | K83: =VLOOKUP(MID(D83,1,LEN(D83)-5),BasicSkills!$B$1:$E$55,3,FALSE) -> Core | L83: =TRIM(MID(D83,1,LEN(D83)-5)) -> Heavy Armor | M83: =A84 -> A combat method created by the Orc clans and turned into a methodical training system. It simply uses any type of middle type of armor and middle type shields to develop the user combat senses. Only one combat method can be active at any time
A84: A combat method created by the Orc clans and turned into a methodical training system. It simply uses any type of middle type of armor and middle type shields to develop the user combat senses. Only one combat method can be active at any time
A85: IronClad Technique (Inter) | D85: Heavy Armor Lv 8 | I85: =A85 -> IronClad Technique (Inter) | J85: =VLOOKUP(MID(D85,1,LEN(D85)-5),BasicSkills!$B$1:$E$55,2,FALSE) -> STR | K85: =VLOOKUP(MID(D85,1,LEN(D85)-5),BasicSkills!$B$1:$E$55,3,FALSE) -> Core | L85: =TRIM(MID(D85,1,LEN(D85)-5)) -> Heavy Armor | M85: =A86 -> A technique for users combining heavy armor and shield, its a technique which armonizes both armor and shield into a single style, only midle level shields and heavy armors can be used in this style.
A86: A technique for users combining heavy armor and shield, its a technique which armonizes both armor and shield into a single style, only midle level shields and heavy armors can be used in this style.
A87: Infantryman Armor Technique (Inter) | D87: Heavy Armor Lv 8 | I87: =A87 -> Infantryman Armor Technique (Inter) | J87: =VLOOKUP(MID(D87,1,LEN(D87)-5),BasicSkills!$B$1:$E$55,2,FALSE) -> STR | K87: =VLOOKUP(MID(D87,1,LEN(D87)-5),BasicSkills!$B$1:$E$55,3,FALSE) -> Core | L87: =TRIM(MID(D87,1,LEN(D87)-5)) -> Heavy Armor | M87: =A88 -> A technique used by hybrid and Middle type armor used to defend a position. Its a technique which maximizes the defense of middle armor while keeping a moderate mobility, you could call it an all around armor mechanic used by most soldiers
A88: A technique used by hybrid and Middle type armor used to defend a position. Its a technique which maximizes the defense of middle armor while keeping a moderate mobility, you could call it an all around armor mechanic used by most soldiers
A89: Juggernaut Armor Technique (Inter) | D89: Heavy Armor Lv 7 | I89: =A89 -> Juggernaut Armor Technique (Inter) | J89: =VLOOKUP(MID(D89,1,LEN(D89)-5),BasicSkills!$B$1:$E$55,2,FALSE) -> STR | K89: =VLOOKUP(MID(D89,1,LEN(D89)-5),BasicSkills!$B$1:$E$55,3,FALSE) -> Core | L89: =TRIM(MID(D89,1,LEN(D89)-5)) -> Heavy Armor | M89: =A90 -> A technique used by heavy and colosal type of armors users, made to be slow but extremely durable, its classically refered as "tank" type technique
A90: A technique used by heavy and colosal type of armors users, made to be slow but extremely durable, its classically refered as "tank" type technique
A91: Heavy Shield Technique (Basic) | D91: Heavy Armor Lv 7 | I91: =A91 -> Heavy Shield Technique (Basic) | J91: =VLOOKUP(MID(D91,1,LEN(D91)-5),BasicSkills!$B$1:$E$55,2,FALSE) -> STR | K91: =VLOOKUP(MID(D91,1,LEN(D91)-5),BasicSkills!$B$1:$E$55,3,FALSE) -> Core | L91: =TRIM(MID(D91,1,LEN(D91)-5)) -> Heavy Armor | M91: =A92 -> A technique focuses on the use of large shields such as tower, knight and kite shields, including all middle and large shields. Its popular for knights and defenders
A92: A technique focuses on the use of large shields such as tower, knight and kite shields, including all middle and large shields. Its popular for knights and defenders
A93: Martial Temperance (Basic) | D93: Discipline Lv 9 | I93: =A93 -> Martial Temperance (Basic) | J93: =VLOOKUP(MID(D93,1,LEN(D93)-5),BasicSkills!$B$1:$E$55,2,FALSE) -> WIL | K93: =VLOOKUP(MID(D93,1,LEN(D93)-5),BasicSkills!$B$1:$E$55,3,FALSE) -> Support | L93: =TRIM(MID(D93,1,LEN(D93)-5)) -> Discipline | M93: =A94 -> A martial warrior cultivates not only the body but also their mind and spirit. This is martial temperament, skill focused on rejecting the outside influences to attain the level of abandonment of oneself
A94: A martial warrior cultivates not only the body but also their mind and spirit. This is martial temperament, skill focused on rejecting the outside influences to attain the level of abandonment of oneself
A95: Soldier's Way (Inter) | D95: Discipline Lv 8 | I95: =A95 -> Soldier's Way (Inter) | J95: =VLOOKUP(MID(D95,1,LEN(D95)-5),BasicSkills!$B$1:$E$55,2,FALSE) -> WIL | K95: =VLOOKUP(MID(D95,1,LEN(D95)-5),BasicSkills!$B$1:$E$55,3,FALSE) -> Support | L95: =TRIM(MID(D95,1,LEN(D95)-5)) -> Discipline | M95: =A96 -> The way of the soldier, a discipline trained to endure harsh conditions and stand in battle witout loosing focus despite the battlefield natural chaos.
A96: The way of the soldier, a discipline trained to endure harsh conditions and stand in battle witout loosing focus despite the battlefield natural chaos.
A97: Bravery (Inter) | D97: Discipline Lv 7 | I97: =A97 -> Bravery (Inter) | J97: =VLOOKUP(MID(D97,1,LEN(D97)-5),BasicSkills!$B$1:$E$55,2,FALSE) -> WIL | K97: =VLOOKUP(MID(D97,1,LEN(D97)-5),BasicSkills!$B$1:$E$55,3,FALSE) -> Support | L97: =TRIM(MID(D97,1,LEN(D97)-5)) -> Discipline | M97: =A98 -> a trained discipline can lead to confront the natural fears, thus becoming someone with great control over one's own weakness, this is mostly focused on fear and terror inducing attacks, but it also works to counter other heart affecting events in lesser measure
A98: a trained discipline can lead to confront the natural fears, thus becoming someone with great control over one's own weakness, this is mostly focused on fear and terror inducing attacks, but it also works to counter other heart affecting events in lesser measure
A99: War Cry (basic) | D99: Intimidation Lv 9 | I99: =A99 -> War Cry (basic) | J99: =VLOOKUP(MID(D99,1,LEN(D99)-5),BasicSkills!$B$1:$E$55,2,FALSE) -> CAR | K99: =VLOOKUP(MID(D99,1,LEN(D99)-5),BasicSkills!$B$1:$E$55,3,FALSE) -> Support | L99: =TRIM(MID(D99,1,LEN(D99)-5)) -> Intimidation | M99: =A100 -> an applied method of using intimidation by roaring or speaking loudly, its effective in the battlefield and sometimes outside of the battlefield
A100: an applied method of using intimidation by roaring or speaking loudly, its effective in the battlefield and sometimes outside of the battlefield
...

Sheet AttributeData
C1: 0 | E1: 1 | G1: 2 | I1: 3 | K1: 4 | M1: 5 | O1: 6 | Q1: 7
C2: 100 - 109 | E2: =CONCATENATE(VALUE(RIGHT(C2,3))+1," - ",VALUE(RIGHT(C2,3))+40) -> 110 - 149 | G2: =CONCATENATE(VALUE(RIGHT(E2,3))+1," - ",VALUE(RIGHT(E2,3))+50) -> 150 - 199 | I2: =CONCATENATE(VALUE(RIGHT(G2,3))+1," - ",VALUE(RIGHT(G2,3))+50) -> 200 - 249 | K2: =CONCATENATE(VALUE(RIGHT(I2,3))+1," - ",VALUE(RIGHT(I2,3))+50) -> 250 - 299 | M2: =CONCATENATE(VALUE(RIGHT(K2,3))+1," - ",VALUE(RIGHT(K2,3))+50) -> 300 - 349 | O2: =CONCATENATE(VALUE(RIGHT(M2,3))+1," - ",VALUE(RIGHT(M2,3))+50) -> 350 - 399 | Q2: 400+ | S2: Traits | U2: Core Skills | W2: penalty 1 | X2: penalty 2 | Y2: Gain 1 | Z2: Gain 2
A3: STR | B3: Raw physical strength, Strength is a measure of your physical power. It affects how much you can carry, and the damage of all melee attacks | C3: Puny Human | D3: Can barely throw a punch. | E3: Loot Carrier | F3: Just here to barely haul gear. | G3: Featherweight | H3: you can live by with normal physical labor | I3: Brawny | J3: strong body and some more | K3: Bruiser | L3: Can take a hit and keep on swinging | M3: Tanky | N3: Tough and powerful, reliable in combat. | O3: Powerhouse | P3: Impressive; can crush through most obstacles | Q3: Juggernaut | R3: A specialist in feats of strength, lifting or smashing anything | S3: Carry Weigt | T3: Melee Damage | U3: Melee Weapons | V3: Armor Handling | X3: WeakArm | Y3: Inner Strenght | Z3: Rubbery Muscles
A4: AGI | B4: Coordination and the ability to move well. Agility is a measure of your overall finesse and reflexes. It affects the your movement rate and natural dodge | C4: Stumbler | D4: Moves with all the grace of a stone rolling uphill. | E4: Cart-Puller | F4: Moves like they’re wading through mud. | G4: Steady | H4: Quick enough for normal life; can dodge and keep up | I4: Nimble Toes | J4: Moves with purpose, maybe even style. | K4: Deft Hands | L4: Steady under pressure, even in precarious spots | M4: Evasionist | N4: Moves with expert control and finesse | O4: SpeedDemon | P4: Gets from A to B fast enough to impress. | Q4: WindStrider | R4: A specialist in dodging and navigating danger. | S4: Movement Speed | T4: Armor Bonus | U4: Brawling | V4: Light Weapons | W4: Lame | X4: Unreactive | Y4: Coordination | Z4: High Tension
A5: INT | B5: Knowledge and the ability to think quickly. Intelligence is a measure of your overall mental acuity. It affects your situacional judgement and overal capacity to learn | C5: No-Brainer | D5: Struggles with most tasks; easily confused. | E5: Rockhead | F5: Thick, slow, and unmoving. | G5: Clearminded | H5: clever and thoughtful for common tasks | I5: Smart Ass | J5: Knows a bit about everything | K5: Problem Solver | L5: Thinks on their feet effectively. | M5: Astute | N5: your average sleuth Quick-witted and perceptive | O5: Savant | P5: a brute force of the mind, capable of solving problems beyond others' reach | Q5: Dr Nerdminator | R5: A true authority on complicated issues, A specialist in knowledge and thought. | S5: Judgement | T5: Memory Slots | U5: Mana Discipline | V5: Mental Focus | W5: Frail Mind | X5: Arcane Fatigue | Y5: Voracious Reader | Z5: Calculus
A6: PER | B6: The ability to see, hear, taste and notice unusual things. Perception affects your awareness of nearby enemies, your ability to detect stealthy movement, and your ability to realice environment changes | C6: Sleeper | D6: Lost in their thoughts most of the time. | E6: Foggy | F6: Notices only what’s directly in front of them. | G6: Half-Awake | H6: Perceptive enough to avoid walking into walls | I6: Early Bird | J6: perceptive enough to catch details before anyone | K6: Hound | L6: Picks up on signs like a hound | M6: FoxChaser | N6: A true bird of prey never lets its target get away | O6: Hawkeye | P6: Always looking for the hidden and distant. | Q6: 3rd Eye | R6: Perception so sharp it borders on supernatural. | S6: Natural Detection | T6: Environment Sensitivity | U6: Projectile Weapons | V6: Still Mind | W6: Murky-Eyed | X6: Inattentive | Y6: Explorer | Z6: Death Sense
A7: WIL | B7: mental fortitude and the ability to think on your feet or practical thinking and common sense, its often related to keeping your composure and using your instincts | C7: Clueless | D7: Lost in every sense of the word | E7: Gut Thinker | F7: Decisions seem to come from their stomach | G7: Cautious | H7: Balances common sense with decisions | I7: Level Headed | J7: a good and cautious head on your shoulders | K7: Truthseeker | L7: Digs out hidden truths and details with his insight | M7: Determined | N7: a unshakeable will to reach the conclusion | O7: Wiseman-ish | P7: Occasionally mistaken for a true sage | Q7: Stargazer | R7: Reads the patterns of the world effortlessly | S7: Guts | T7: Composure | U7: Piety | V7: Mana Sensitivity | W7: Naive | X7: Ascetic | Y7: Stoic | Z7: Pain Tolerance
A8: CHA | B8: A combination of appearance, presence and charm. Charisma is your ability to lead and help others and affects your gut feelings or emphatic sensitivity | C8: Wallflower | D8: Blends into the background (and not on purpose). | E8: Fumbletongue | F8: struggles to say the right thing | G8: Barely Friendly | H8: Likeable enough to win a handshake | I8: Firestarter | J8: Draws others in with warmth and energy | K8: Crowdpleaser | L8: A relatable and likable personality | M8: Heartbreaker | N8: Spins words and emotions like threads | O8: Silvertounge | P8: Speaks with persuasion and charm | Q8: Wordsmith | R8: Words so powerful they could topple thrones | S8: Empathy | T8: Charm | U8: Faith | V8: Nature Focus | W8: Irrelevant | X8: Toad | Y8: Inspirational | Z8: Karmic Beacon
A9: BOD | B9: Stamina and physical toughness, a measure of overall physical fitness. It affects your total health and your overall ability to handle fatigue | C9: Frail | D9: a frail body often sickly | G9: Healthy | H9: a simple common healthy body | K9: Robust | L9: a strong body able to endure most ordeals | O9: Booming | P9: an iron body forged on pure effort that can withstand anything | S9: Stamina | T9: Toughness | W9: Small | X9: Sickly | Y9: Big | Z9: Browny
A10: MND | B10: learning and inspiration, a measure of your mind power and overall overclocking capacity. It advantages your growth each level and insight to derive things | C10: Bumbling | D10: liable to make awkward blunder, clumsily incompetent or ineffectual | G10: Slacker | H10: commonly evades their duty or work | K10: Skilled | L10: a skilled and dilligent person that easily absorbs anything | O10: Brilliant | P10: a brilliant person capable of learning anything | S10: Inspiration | T10: PP | W10: One Trick Pony | X10: Savant Syndrome | Y10: Talented | Z10: Higher Education
A11: SPR | B11: supernatual sense and spirit awareness, a measure of your overall morale and confidence, it affects your total Mana and your ability to handle stress | C11: Lethargic | D11: little will to live, a spirit not very different from plants | G11: Craven | H11: a weak spirit that easily bends | K11: Bold | L11: a strong spirit that can step forward in face of dangers | O11: Dauntless | P11: a fearless person that shines in the moments of needs | S11: Morale | T11: Awareness | W11: Coward | X11: Driven | Y11: LionHeart | Z11: Strong Spirit
A12: VIT | B12: a measure of your overall vigor or physical energy, it directly affects your HP and your overall recovery | C12: Withered Husk | D12: a husk with little amount of lifeforce, barely alive | G12: ToughCookie | H12: Can take a beating, Not impressive, but not embarrassing either | K12: Meatshield | L12: a strong lifeforce that stubbornly clinges to life despite damage | O12: Inmortal Wannabe | P12: a relentless lifeforce that never gives up like a weed that seems untouchable by death | S12: Recovery (HP) | T12: HP | W12: Hard to Heal | X12: Phantom Pain | Y12: Easy to Heal | Z12: Scorpion Eater
A13: AST | B13: a measure of your overall mana attunement or mystical energy, it directly affects your MP and your spiritual recovery | C13: Sparkless | D13: struggles to feel or understand any form of mana | G13: Burntout | H13: a common person that requieres great effort to reach the mystical force | K13: Glowstick | L13: a strong mana that can be seen in the subtle glow of their irises | O13: Overloaded | P13: a person with abundant mana that can be perceived in most of their actions | S13: Recovery (MP) | T13: MP | W13: Lunatic | X13: LucidProne | Y13: Spirit Recovery | Z13: Mana Core
A14: FATE | B14: a measure of general good fortune, and affects the player interference on the character's circumstances and Events / situations will be changed by how lucky (or unlucky) your character is | C14: Doom Chaser | D14: Always stumbling into the worst possible outcomes | G14: Fate’s Fool | H14: Life feels like a cruel joke, and they’re the punchline. | K14: Fate’s Magnet | L14: Seems like fate is still figuring them out | O14: Choosen-ish | P14: FATE clearly likes them, but not too much | S14: Fortune | T14: Inteference | W14: Trouble Magnet | X14: Critical Miss | Y14: Lucky! | Z14: Fortune Finder
A15: 0 | B15: 1 | C15: 2 | D15: 3 | E15: 4 | F15: 5 | G15: 6 | H15: 7 | I15: 8 | J15: 9 | K15: 10 | L15: 11 | M15: 12 | N15: 13 | O15: 14 | P15: 15 | Q15: 16 | R15: 17 | S15: 18 | T15: 19 | U15: 20 | V15: 21 | W15: 22 | X15: 23 | Y15: 24 | Z15: 25
A16: 0 | B16: 1 | C16: 2 | D16: 2 | E16: 2 | F16: 2 | G16: 2 | H16: 2 | I16: 2 | J16: 2 | K16: 2 | L16: 2 | M16: 2 | N16: 2 | O16: 2 | P16: 2 | Q16: 2 | R16: 2
C17: =(C15-2)*2 -> 0 | D17: =D15-2 -> 1 | E17: =C17+2 -> 2 | F17: =D17+2 -> 3 | G17: =E17+2 -> 4 | H17: =F17+2 -> 5 | I17: =G17+2 -> 6 | J17: =H17+2 -> 7 | K17: =I17+2 -> 8 | L17: =J17+2 -> 9 | ... R17: =P17+2 -> 15
C18: =C17+C16 -> 2 | D18: =D17+D16 -> 3 | E18: =E17+E16 -> 4 | F18: =F17+F16 -> 5 | G18: =G17+G16 -> 6 | H18: =H17+H16 -> 7 | I18: =I17+I16 -> 8 | J18: =J17+J16 -> 9 | ... R18: =R17+R16 -> 17
B20: 0 | C20: 1 | D20: 2 | E20: 3 | F20: 4 | G20: 5 | H20: 6
B21: 110 | C21: =C20*40+$B$21+MAX(0,C20-1)*10 -> 150 | D21: =D20*40+$B$21+MAX(0,D20-1)*10 -> 200 | E21: =E20*40+$B$21+MAX(0,E20-1)*10 -> 250 | F21: =F20*40+$B$21+MAX(0,F20-1)*10 -> 300 | G21: =G20*40+$B$21+MAX(0,G20-1)*10 -> 350 | H21: =H20*40+$B$21+MAX(0,H20-1)*10 -> 400
B23: =IF(B21<260,B21,A23) -> 110 | C23: =IF(C21<260,C21,B23) -> 150 | D23: =IF(D21<260,D21,C23) -> 200 | E23: =IF(E21<260,E21,D23) -> 250 | F23: =IF(F21<260,F21,E23) -> 250 | G23: =IF(G21<260,G21,F23) -> 250 | H23: =IF(H21<260,H21,G23) -> 250
C24: =110 + (C18-2)*40+MAX(0,C18-3)*10 -> 110 | E24: =110 + (E18-2)*20+MAX(0,E18-4)*10 -> 150 | G24: =110 + (G18-2)*20+MAX(0,G18-4)*5 -> 200 | I24: =110 + (I18-2)*20+MAX(0,I18-4)*5 -> 250 | K24: =110 + (K18-2)*20+MAX(0,K18-4)*5 -> 300 | M24: =110 + (M18-2)*20+MAX(0,M18-4)*5 -> 350 | O24: =110 + (O18-2)*20+MAX(0,O18-4)*5 -> 400
E25: =IF(E24<150,E3,C28) -> 0 | G25: =IF(G24<150,G3,E25) -> 0
B28: 100 | C28: =IF($C$24<=B28,$C$3,0) -> 0 | D28: =IF($C$24>=B28,$C$3,0) -> Puny Human
B29: 110 | C29: =IF($C$24<=B29,$C$3,0) -> Puny Human | D29: =IF($C$24>=B29,$C$3,0) -> Puny Human
B30: 120 | C30: =IF($C$24<=B30,$C$3,0) -> Puny Human | D30: =IF($C$24>=B30,$C$3,0) -> 0
B31: 130 | C31: =IF($C$24<=B31,$C$3,0) -> Puny Human | D31: =IF($C$24>=B31,$C$3,0) -> 0
B32: 140 | C32: =IF($C$24<=B32,$C$3,0) -> Puny Human | D32: =IF($C$24>=B32,$C$3,0) -> 0
B33: 150 | C33: =IF($C$24<=B33,$C$3,0) -> Puny Human | D33: =IF($C$24>=B33,$C$3,0) -> 0
B34: 160 | C34: =IF($C$24<=B34,$C$3,0) -> Puny Human | D34: =IF($C$24>=B34,$C$3,0) -> 0
B35: 170
B36: 180
B37: 190
B38: 200
B39: 210
B40: 220
B41: 230
B42: 240
B43: 250
B44: 260
B45: 270
B46: 280
... B58: 400
